Workbook
Name SegmentaciónDeDatos_Resumen_Vicente: #N/A

Sheet Resumen Por Acreedor
A2: Situación | B2: (Todas)
A4: Razón Social Acreedor | B4: Monto $
A5: Agrícola Ancalí Ltda | B5: 316
A6: Alto Cautín SpA | B6: 14950
A7: Andes Generación SpA | B7: 1431569
A8: CE CENTINELA SOLAR SPA | B8: 82570
A9: CE Uribe de Antofagasta Solar SpA | B9: 777616
A10: Central Cardones S.A. | B10: 5806845
A11: Central Colmito S.A. | B11: 27203199
A12: Central Yungay S.A. | B12: 37397764
A13: Chungungo S.A. | B13: 235199
A14: Chungungo Solar SpA | B14: 2897302
A15: CINERGIA Chile SpA | B15: 52742
A16: Colbún S.A. | B16: 110580829
... A94: Total general | B94: 514934265

Sheet TD
A1: Situación | B1: Abierta
F2: Situación | G2: Abierta
A3: Categoria | B3: Monto bruto | C3: Nemotécnico
A4: cierre solicitado | B4: 2466049 | C4: 2 | F4: Resumen | G4: Observación | H4: N°Disc | I4: Plazo | J4: Accion | K4: Monto bruto | L4: Recuento
A5: En Gestion | B5: 23127955 | C5: 31 | F5: cierre solicitado | G5: Con observacion | H5: DISC_327185 | I5: 16-09-2025 | J5: Se deja observacion para que refacturen exento de iva | K5: 1629820 | L5: 1
A6: Total general | B6: 25594004 | C6: 33 | H6: DISC_328372 | I6: 19-09-2025 | J6: Se deja observacion para que refacturen exento de iva | K6: 836229 | L6: 1
F7: Total cierre solicitado | K7: 2466049 | L7: 2
F8: En Gestion | G8: Coordinado Rechaza Cierre | H8: DISC_326204 | I8: 08-09-2025 | J8: se rechaza cierre por parte del coordinado, no puede emitir exento | K8: 137103 | L8: 1
H9: DISC_341053 | I9: 30-10-2025 | J9: se rechaza cierre por parte del coordinado, no se especifica que el cobro es exento | K9: 103544 | L9: 1
H10: DISC_341078 | I10: 30-10-2025 | J10: se rechaza cierre por parte del coordinado, no se especifica que el cobro es exento | K10: 613624 | L10: 1
H11: DISC_341100 | I11: 30-10-2025 | J11: se rechaza cierre por parte del coordinado, no se especifica que el cobro es exento | K11: 104546 | L11: 1
G12: Enviar a pago | H12: DISC_349676 | I12: 21-11-2025 | J12: enviar hes a la ale | K12: 411 | L12: 1
H13: DISC_349677 | I13: 21-11-2025 | J13: enviar hes a la ale | K13: 12171 | L13: 1
H14: DISC_349679 | I14: 21-11-2025 | J14: enviar hes a la ale | K14: 45 | L14: 1
G15: Nueva | H15: DISC_350902 | I15: 24-11-2025 | J15: Investigar | K15: 71 | L15: 1
H16: DISC_350903 | I16: 24-11-2025 | J16: Investigar | K16: 77 | L16: 1
H17: DISC_350904 | I17: 24-11-2025 | J17: Investigar | K17: 40 | L17: 1
H18: DISC_350905 | I18: 24-11-2025 | J18: Investigar | K18: 14 | L18: 1
H19: DISC_350972 | I19: 24-11-2025 | J19: Investigar | K19: 64393 | L19: 1
H20: DISC_351238 | I20: 25-11-2025 | J20: Investigar | K20: 13111749 | L20: 1
H21: DISC_353295 | I21: 01-12-2025 | J21: Investigar | K21: 282442 | L21: 1
H22: DISC_353298 | I22: 01-12-2025 | J22: Investigar | K22: 60640 | L22: 1
H23: DISC_353456 | I23: 01-12-2025 | J23: Investigar | K23: 71021 | L23: 1
H24: DISC_354762 | I24: 03-12-2025 | J24: Investigar | K24: 6251 | L24: 1
H25: DISC_354763 | I25: 03-12-2025 | J25: Investigar | K25: 196534 | L25: 1
H26: DISC_354764 | I26: 03-12-2025 | J26: Investigar | K26: 6346 | L26: 1
H27: DISC_354765 | I27: 03-12-2025 | J27: Investigar | K27: 6097 | L27: 1
... H38: DISC_356389 | I38: 08-12-2025 | J38: Investigar | K38: 1460770 | L38: 1
F39: Total En Gestion | K39: 23127955 | L39: 31
F40: Total general | K40: 25594004 | L40: 33

Sheet Datos
A1: Activity | B1: Estado de la tarea | C1: Fecha Creación del caso hasta | D1: Current User - Full Name | E1: Nemotécnico | F1: Rut Acreedor (malo) | G1: Razón Social Acreedor | H1: Rut Deudor 77316204-2 | I1: Razón Social Deudor | J1: Tipo de Disconformidad | K1: Monto bruto instrucción de pago | L1: Saldo Pendiente (Neto) | M1: Número de Disconformidad | N1: Fecha de Vencimiento Desde | O1: ¿Disconformidad Abierta por? | P1: Tipo de Disconformidad2 | Q1: En Espera de Ejecución | R1: Mes | S1: Plazo (10 Dias habiles [Columna C]) | T1: N° Acreedor | U1: N° factura | V1: Filtro Abiertas | W1: OC | X1: HES | Y1: Tiene oc y hes? Fecha lib | Z1: Observación (tiempo de gestion prom 7 MIN X Dis) | AA1: resposable | AB1: Situación | AC1: RUT ACREEDOR | AD1: Accion | AE1: Resumen Vicente
B2: Cerrado | C2: 45005.679 | E2: [DISC_38061][P][SEN_[TEE_][Oct22][L][V01]][4673965] | F2: 766165389 | G2: Innovación Energía S.A. | H2: 77316204 | I2: CGE COMERCIALIZADORA SPA | J2: Pago | K2: 201828 | L2: 201828 | M2: DISC_38061 | N2: 44902 | O2: Acreedor | P2: Pago | Q2: No | R2: =+MONTH(C2) | T2: 1025977 | AB2: Cerrada | AC2: =+VLOOKUP(T2,'BBDD ACREEDORES'!$B:$C,2,0) | AE2: =IF(AB2="Abierta",V2,"Cerrada")
B3: Cerrado | C3: 45033.743 | E3: [DISC_41718][P][SEN_[BP__][Sep22][L][V01]][4518794] | F3: 762037882 | G3: Andes Generación SpA | H3: 77316204 | I3: CGE COMERCIALIZADORA SPA | J3: Pago | K3: 30529 | L3: 30529 | M3: DISC_41718 | N3: 45037.413 | O3: Acreedor | P3: Pago | Q3: No | R3: =+MONTH(C3) | T3: 1021658 | AB3: Cerrada | AC3: =+VLOOKUP(T3,'BBDD ACREEDORES'!$B:$C,2,0) | AE3: =IF(AB3="Abierta",V3,"Cerrada")
B4: Cerrado | C4: 45051.631 | E4: [DISC_43630][P][SEN_[CUN_][Feb23][L][V01]][5318610] | F4: 767876904 | G4: Transmisora Eléctrica del Norte S.A. | H4: 77316204 | I4: CGE COMERCIALIZADORA SPA | J4: Pago | K4: 8613734 | L4: 8613734 | M4: DISC_43630 | N4: 45026 | O4: Acreedor | P4: Pago | Q4: No | R4: =+MONTH(C4) | T4: 1024418 | AB4: Cerrada | AC4: =+VLOOKUP(T4,'BBDD ACREEDORES'!$B:$C,2,0) | AE4: =IF(AB4="Abierta",V4,"Cerrada")
B5: Cerrado | C5: 45076.741 | E5: [DISC_47514][P][SEN_[TEE_][Ene23][L][V01]][5140524] | F5: 770606691 | G5: PFV Las Cachañas SpA | H5: 77316204 | I5: CGE COMERCIALIZADORA SPA | J5: Pago | K5: 99518 | L5: 99518 | M5: DISC_47514 | N5: 1/1/1753 12:00:00 AM | O5: Acreedor | P5: Pago | Q5: No | R5: =+MONTH(C5) | T5: 1027702 | AB5: Cerrada | AC5: =+VLOOKUP(T5,'BBDD ACREEDORES'!$B:$C,2,0) | AE5: =IF(AB5="Abierta",V5,"Cerrada")
B6: Cerrado | C6: 45079.408 | E6: [DISC_49354][P][SEN_[CUN_][Mar23][L][V01]][5402659] | F6: 767876904 | G6: Transmisora Eléctrica del Norte S.A. | H6: 77316204 | I6: CGE COMERCIALIZADORA SPA | J6: Pago | K6: 9395862 | L6: 9395862 | M6: DISC_49354 | N6: 45055 | O6: Acreedor | P6: Pago | Q6: No | R6: =+MONTH(C6) | T6: 1024418 | AB6: Cerrada | AC6: =+VLOOKUP(T6,'BBDD ACREEDORES'!$B:$C,2,0) | AE6: =IF(AB6="Abierta",V6,"Cerrada")
B7: Cerrado | C7: 45082.662 | E7: [DISC_51124][P][SEN_[BP__][Abr23][L][V01]][5433273] | F7: 760718912 | G7: Hidroelectrica Allipén S.A. | H7: 77316204 | I7: CGE COMERCIALIZADORA SPA | J7: Pago | K7: 2740 | L7: 2740 | M7: DISC_51124 | N7: 45086.331 | O7: Acreedor | P7: Pago | Q7: No | R7: =+MONTH(C7) | T7: 1015404 | AB7: Cerrada | AC7: =+VLOOKUP(T7,'BBDD ACREEDORES'!$B:$C,2,0) | AE7: =IF(AB7="Abierta",V7,"Cerrada")
B8: Cerrado | C8: 45082.662 | E8: [DISC_51125][P][SEN_[TEE_][Abr23][L][V01]][5466791] | F8: 760718912 | G8: Hidroelectrica Allipén S.A. | H8: 77316204 | I8: CGE COMERCIALIZADORA SPA | J8: Pago | K8: 104048 | L8: 104048 | M8: DISC_51125 | N8: 45086.332 | O8: Acreedor | P8: Pago | Q8: No | R8: =+MONTH(C8) | T8: 1015404 | AB8: Cerrada | AC8: =+VLOOKUP(T8,'BBDD ACREEDORES'!$B:$C,2,0) | AE8: =IF(AB8="Abierta",V8,"Cerrada")
B9: Cerrado | C9: 45082.687 | E9: [DISC_51219][P][SEN_[BP__][Abr23][L][V01]][5433447] | F9: 768340005 | G9: Hidroelectrica Trueno S.A. | H9: 77316204 | I9: CGE COMERCIALIZADORA SPA | J9: Pago | K9: 1505 | L9: 1505 | M9: DISC_51219 | N9: 45086.356 | O9: Acreedor | P9: Pago | Q9: No | R9: =+MONTH(C9) | T9: 1026449 | AB9: Cerrada | AC9: =+VLOOKUP(T9,'BBDD ACREEDORES'!$B:$C,2,0) | AE9: =IF(AB9="Abierta",V9,"Cerrada")
B10: Cerrado | C10: 45082.703 | E10: [DISC_51261][P][SEN_[BP__][Abr23][L][V01]][5433607] | F10: 995896206 | G10: Hidroelectrica Puclaro S.A. | H10: 77316204 | I10: CGE COMERCIALIZADORA SPA | J10: Pago | K10: 6255 | L10: 6255 | M10: DISC_51261 | N10: 45086.372 | O10: Acreedor | P10: Pago | Q10: No | R10: =+MONTH(C10) | T10: 1014010 | AB10: Cerrada | AC10: =+VLOOKUP(T10,'BBDD ACREEDORES'!$B:$C,2,0) | AE10: =IF(AB10="Abierta",V10,"Cerrada")
B11: Cerrado | C11: 45082.703 | E11: [DISC_51262][P][SEN_[TEE_][Abr23][L][V01]][5467130] | F11: 995896206 | G11: Hidroelectrica Puclaro S.A. | H11: 77316204 | I11: CGE COMERCIALIZADORA SPA | J11: Pago | K11: 37312 | L11: 37312 | M11: DISC_51262 | N11: 45086.372 | O11: Acreedor | P11: Pago | Q11: No | R11: =+MONTH(C11) | T11: 1014010 | AB11: Cerrada | AC11: =+VLOOKUP(T11,'BBDD ACREEDORES'!$B:$C,2,0) | AE11: =IF(AB11="Abierta",V11,"Cerrada")
B12: Cerrado | C12: 45083.372 | E12: [DISC_51458][P][SEN_[BP__][Abr23][L][V01]][5433518] | F12: 760551368 | G12: Hidroeléctrica Mallarauco S.A. | H12: 77316204 | I12: CGE COMERCIALIZADORA SPA | J12: Pago | K12: 3780 | L12: 3780 | M12: DISC_51458 | N12: 45089.041 | O12: Acreedor | P12: Pago | Q12: No | R12: =+MONTH(C12) | T12: 1021439 | AB12: Cerrada | AC12: =+VLOOKUP(T12,'BBDD ACREEDORES'!$B:$C,2,0) | AE12: =IF(AB12="Abierta",V12,"Cerrada")
B13: Cerrado | C13: 45083.372 | E13: [DISC_51459][P][SEN_[TEE_][Abr23][L][V01]][5467039] | F13: 760551368 | G13: Hidroeléctrica Mallarauco S.A. | H13: 77316204 | I13: CGE COMERCIALIZADORA SPA | J13: Pago | K13: 6320 | L13: 6320 | M13: DISC_51459 | N13: 45089.042 | O13: Acreedor | P13: Pago | Q13: No | R13: =+MONTH(C13) | T13: 1021439 | AB13: Cerrada | AC13: =+VLOOKUP(T13,'BBDD ACREEDORES'!$B:$C,2,0) | AE13: =IF(AB13="Abierta",V13,"Cerrada")
B14: Cerrado | C14: 45083.401 | E14: [DISC_51522][P][SEN_[BP__][Abr23][L][V01]][5433635] | F14: 760711136 | G14: Hidroeléctrica Río Huasco S.A. | H14: 77316204 | I14: CGE COMERCIALIZADORA SPA | J14: Pago | K14: 6361 | L14: 6361 | M14: DISC_51522 | N14: 45089.07 | O14: Acreedor | P14: Pago | Q14: No | R14: =+MONTH(C14) | T14: 1016827 | AB14: Cerrada | AC14: =+VLOOKUP(T14,'BBDD ACREEDORES'!$B:$C,2,0) | AE14: =IF(AB14="Abierta",V14,"Cerrada")
B15: Cerrado | C15: 45083.401 | E15: [DISC_51523][P][SEN_[TEE_][Abr23][L][V01]][5467158] | F15: 760711136 | G15: Hidroeléctrica Río Huasco S.A. | H15: 77316204 | I15: CGE COMERCIALIZADORA SPA | J15: Pago | K15: 51690 | L15: 51690 | M15: DISC_51523 | N15: 45089.071 | O15: Acreedor | P15: Pago | Q15: No | R15: =+MONTH(C15) | T15: 1016827 | AB15: Cerrada | AC15: =+VLOOKUP(T15,'BBDD ACREEDORES'!$B:$C,2,0) | AE15: =IF(AB15="Abierta",V15,"Cerrada")
B16: Cerrado | C16: 45083.464 | E16: [DISC_51843][P][SEN_[BP__][Abr23][L][V01]][5433374] | F16: 762640252 | G16: Hidroeléctrica Embalse Ancoa SpA | H16: 77316204 | I16: CGE COMERCIALIZADORA SPA | J16: Pago | K16: 7389 | L16: 7389 | M16: DISC_51843 | N16: 45089.133 | O16: Acreedor | P16: Pago | Q16: No | R16: =+MONTH(C16) | T16: 1023872 | AB16: Cerrada | AC16: =+VLOOKUP(T16,'BBDD ACREEDORES'!$B:$C,2,0) | AE16: =IF(AB16="Abierta",V16,"Cerrada")
B17: Cerrado | C17: 45083.464 | E17: [DISC_51844][P][SEN_[TEE_][Abr23][L][V01]][5466896] | F17: 762640252 | G17: Hidroeléctrica Embalse Ancoa SpA | H17: 77316204 | I17: CGE COMERCIALIZADORA SPA | J17: Pago | K17: 145700 | L17: 145700 | M17: DISC_51844 | N17: 45089.134 | O17: Acreedor | P17: Pago | Q17: No | R17: =+MONTH(C17) | T17: 1023872 | AB17: Cerrada | AC17: =+VLOOKUP(T17,'BBDD ACREEDORES'!$B:$C,2,0) | AE17: =IF(AB17="Abierta",V17,"Cerrada")
... B31: Cerrado | C31: 45091.725 | E31: [DISC_53382][P][SEN_[SCRT][Abr23][L][V01]][5491094] | F31: 760093289 | G31: Enlasa Generación Chile S.A. | H31: 77316204 | I31: CGE COMERCIALIZADORA SPA | J31: Pago | K31: 252546 | L31: 252546 | M31: DISC_53382 | N31: 45078 | O31: Acreedor | P31: Pago | Q31: No | R31: =+MONTH(C31) | T31: 1007718 | AB31: Cerrada | AC31: =+VLOOKUP(T31,'BBDD ACREEDORES'!$B:$C,2,0) | AE31: =IF(AB31="Abierta",V31,"Cerrada")
A32: Gestión de Cierre Disconformidad - Espera Resolución Cierre - Cierre Anticipado - Seguimiento Acreedor - Seguimiento Deudor - CANCELAR | B32: Cerrado | C32: 45091.753 | D32: - Sin Asignar - Pablo Montero - Paola Ahumada - Usuario Pivot | E32: [DISC_53392][P][SEN_[TEE_][Abr23][L][V01]][5466991] | F32: 760370363 | G32: Empresa Eléctrica La Arena SpA | H32: 77316204 | I32: CGE COMERCIALIZADORA SPA | J32: Pago | K32: 119249 | L32: 119249 | M32: DISC_53392 | N32: 45097.423 | O32: Acreedor | P32: Pago | Q32: No | R32: =+MONTH(C32) | S32: =+C32+14 | T32: 1014070 | U32: 10466 | W32: Pagado 29/6 | AB32: Cerrada | AC32: =+VLOOKUP(T32,'BBDD ACREEDORES'!$B:$C,2,0) | AE32: =IF(AB32="Abierta",V32,"Cerrada")
A33: Gestión de Cierre Disconformidad - Espera Resolución Cierre - Seguimiento Deudor - Cierre Anticipado - Seguimiento Acreedor - CANCELAR | B33: Cerrado | C33: 45091.754 | D33: - Sin Asignar - Usuario Pivot | E33: [DISC_53395][P][SEN_[BP__][Abr23][L][V01]][5433470] | F33: 760370363 | G33: Empresa Eléctrica La Arena SpA | H33: 77316204 | I33: CGE COMERCIALIZADORA SPA | J33: Pago | K33: 3560 | L33: 3560 | M33: DISC_53395 | N33: 45097.423 | O33: Acreedor | P33: Pago | Q33: No | R33: =+MONTH(C33) | S33: =+C33+14 | T33: 1014070 | U33: 10550 | W33: Pagado 29/6 | AB33: Cerrada | AC33: =+VLOOKUP(T33,'BBDD ACREEDORES'!$B:$C,2,0) | AE33: =IF(AB33="Abierta",V33,"Cerrada")
A34: Cierre Anticipado - Seguimiento Acreedor - Seguimiento Deudor - Espera Movimientos - Espera Ejecución en P. de Garantías - CANCELAR | B34: Cerrado | C34: 45091.768 | D34: Sin Asignar - Paola Ahumada - Usuario Pivot | E34: [DISC_53411][P][SEN_[TEE_][Abr23][L][V01]][5466884] | F34: 763622681 | G34: Empresa Eléctrica Tranquil S.P.A | H34: 77316204 | I34: CGE COMERCIALIZADORA SPA | J34: Pago | K34: 33515 | L34: 33515 | M34: DISC_53411 | N34: 45097.437 | O34: Acreedor | P34: Pago | Q34: Si | R34: =+MONTH(C34) | T34: 1023007 | U34: 10434 | W34: Pagado 29/6 | AB34: Cerrada | AC34: =+VLOOKUP(T34,'BBDD ACREEDORES'!$B:$C,2,0) | AE34: =IF(AB34="Abierta",V34,"Cerrada")
A35: Gestión de Cierre Disconformidad - Espera Resolución Cierre - Seguimiento Deudor - Cierre Anticipado - Seguimiento Acreedor - CANCELAR | B35: Cerrado | C35: 45091.768 | D35: - Sin Asignar - Usuario Pivot | E35: [DISC_53412][P][SEN_[BP__][Abr23][L][V01]][5433360] | F35: 763622681 | G35: Empresa Eléctrica Tranquil S.P.A | H35: 77316204 | I35: CGE COMERCIALIZADORA SPA | J35: Pago | K35: 2353 | L35: 2353 | M35: DISC_53412 | N35: 45097.437 | O35: Acreedor | P35: Pago | Q35: No | R35: =+MONTH(C35) | S35: =+C35+14 | T35: 1023007 | U35: 10517 | W35: Pagado 29/6 | AB35: Cerrada | AC35: =+VLOOKUP(T35,'BBDD ACREEDORES'!$B:$C,2,0) | AE35: =IF(AB35="Abierta",V35,"Cerrada")
B36: Cerrado | C36: 45092.457 | E36: [DISC_53459][P][SEN_[BP__][Abr23][L][V01]][5433538] | F36: 762652870 | G36: Generación de Energía Nueva Degan SpA | H36: 77316204 | I36: CGE COMERCIALIZADORA SPA | J36: Pago | K36: 64841 | L36: 64841 | M36: DISC_53459 | N36: 45098.126 | O36: Acreedor | P36: Pago | Q36: No | R36: =+MONTH(C36) | T36: 1016242 | AB36: Cerrada | AC36: =+VLOOKUP(T36,'BBDD ACREEDORES'!$B:$C,2,0) | AE36: =IF(AB36="Abierta",V36,"Cerrada")
B37: Cerrado | C37: 45092.457 | E37: [DISC_53460][P][SEN_[TEE_][Abr23][L][V01]][5467060] | F37: 762652870 | G37: Generación de Energía Nueva Degan SpA | H37: 77316204 | I37: CGE COMERCIALIZADORA SPA | J37: Pago | K37: 14738 | L37: 14738 | M37: DISC_53460 | N37: 45098.126 | O37: Acreedor | P37: Pago | Q37: No | R37: =+MONTH(C37) | T37: 1016242 | AB37: Cerrada | AC37: =+VLOOKUP(T37,'BBDD ACREEDORES'!$B:$C,2,0) | AE37: =IF(AB37="Abierta",V37,"Cerrada")
B38: Cerrado | C38: 45092.488 | E38: [DISC_53504][P][SEN_[BP__][Abr23][L][V01]][5433282] | F38: 76009904k | G38: Generadora Antilhue Spa | H38: 77316204 | I38: CGE COMERCIALIZADORA SPA | J38: Pago | K38: 120144 | L38: 120144 | M38: DISC_53504 | N38: 45098.157 | O38: Acreedor | P38: Pago | Q38: No | R38: =+MONTH(C38) | T38: 1025760 | AB38: Cerrada | AC38: =+VLOOKUP(T38,'BBDD ACREEDORES'!$B:$C,2,0) | AE38: =IF(AB38="Abierta",V38,"Cerrada")
B39: Cerrado | C39: 45092.488 | E39: [DISC_53505][P][SEN_[SCRT][Abr23][L][V01]][5491088] | F39: 76009904k | G39: Generadora Antilhue Spa | H39: 77316204 | I39: CGE COMERCIALIZADORA SPA | J39: Pago | K39: 260324 | L39: 260324 | M39: DISC_53505 | N39: 45098.157 | O39: Acreedor | P39: Pago | Q39: No | R39: =+MONTH(C39) | T39: 1025760 | AB39: Cerrada | AC39: =+VLOOKUP(T39,'BBDD ACREEDORES'!$B:$C,2,0) | AE39: =IF(AB39="Abierta",V39,"Cerrada")
B40: Cerrado | C40: 45092.488 | E40: [DISC_53506][P][SEN_[TEE_][Abr23][L][V01]][5466801] | F40: 76009904k | G40: Generadora Antilhue Spa | H40: 77316204 | I40: CGE COMERCIALIZADORA SPA | J40: Pago | K40: 364752 | L40: 364752 | M40: DISC_53506 | N40: 45098.158 | O40: Acreedor | P40: Pago | Q40: No | R40: =+MONTH(C40) | T40: 1025760 | AB40: Cerrada | AC40: =+VLOOKUP(T40,'BBDD ACREEDORES'!$B:$C,2,0) | AE40: =IF(AB40="Abierta",V40,"Cerrada")
B41: Cerrado | C41: 45092.507 | E41: [DISC_53529][P][SEN_[TEE_][Abr23][L][V01]][5466983] | F41: 772529457 | G41: Inversiones Chacabuco SpA | H41: 77316204 | I41: CGE COMERCIALIZADORA SPA | J41: Pago | K41: 126266 | L41: 126266 | M41: DISC_53529 | N41: 45098.176 | O41: Acreedor | P41: Pago | Q41: No | R41: =+MONTH(C41) | T41: 1026424 | AB41: Cerrada | AC41: =+VLOOKUP(T41,'BBDD ACREEDORES'!$B:$C,2,0) | AE41: =IF(AB41="Abierta",V41,"Cerrada")
B42: Cerrado | C42: 45092.507 | E42: [DISC_53530][P][SEN_[BP__][Abr23][L][V01]][5433464] | F42: 772529457 | G42: Inversiones Chacabuco SpA | H42: 77316204 | I42: CGE COMERCIALIZADORA SPA | J42: Pago | K42: 3308 | L42: 3308 | M42: DISC_53530 | N42: 45098.176 | O42: Acreedor | P42: Pago | Q42: No | R42: =+MONTH(C42) | T42: 1026424 | AB42: Cerrada | AC42: =+VLOOKUP(T42,'BBDD ACREEDORES'!$B:$C,2,0) | AE42: =IF(AB42="Abierta",V42,"Cerrada")
B43: Cerrado | C43: 45092.555 | E43: [DISC_53551][P][SEN_[BP__][Abr23][L][V01]][5433664] | F43: 772619561 | G43: Solar la Blanquina SpA | H43: 77316204 | I43: CGE COMERCIALIZADORA SPA | J43: Pago | K43: 3098 | L43: 3098 | M43: DISC_53551 | N43: 45098.224 | O43: Acreedor | P43: Pago | Q43: No | R43: =+MONTH(C43) | T43: 1026425 | AB43: Cerrada | AC43: =+VLOOKUP(T43,'BBDD ACREEDORES'!$B:$C,2,0) | AE43: =IF(AB43="Abierta",V43,"Cerrada")
B44: Cerrado | C44: 45092.555 | E44: [DISC_53552][P][SEN_[TEE_][Abr23][L][V01]][5467185] | F44: 772619561 | G44: Solar la Blanquina SpA | H44: 77316204 | I44: CGE COMERCIALIZADORA SPA | J44: Pago | K44: 78897 | L44: 78897 | M44: DISC_53552 | N44: 45098.225 | O44: Acreedor | P44: Pago | Q44: No | R44: =+MONTH(C44) | T44: 1026425 | AB44: Cerrada | AC44: =+VLOOKUP(T44,'BBDD ACREEDORES'!$B:$C,2,0) | AE44: =IF(AB44="Abierta",V44,"Cerrada")
B45: Cerrado | C45: 45092.585 | E45: [DISC_53578][P][SEN_[BP__][Abr23][L][V01]][5433399] | F45: 770420326 | G45: Fontus Prime Solar SpA | H45: 77316204 | I45: CGE COMERCIALIZADORA SPA | J45: Pago | K45: 25821 | L45: 25821 | M45: DISC_53578 | N45: 45098.254 | O45: Acreedor | P45: Pago | Q45: No | R45: =+MONTH(C45) | T45: 1027439 | AB45: Cerrada | AC45: =+VLOOKUP(T45,'BBDD ACREEDORES'!$B:$C,2,0) | AE45: =IF(AB45="Abierta",V45,"Cerrada")
B46: Cerrado | C46: 45092.585 | E46: [DISC_53579][P][SEN_[TEE_][Abr23][L][V01]][5466918] | F46: 770420326 | G46: Fontus Prime Solar SpA | H46: 77316204 | I46: CGE COMERCIALIZADORA SPA | J46: Pago | K46: 968613 | L46: 968613 | M46: DISC_53579 | N46: 45098.254 | O46: Acreedor | P46: Pago | Q46: No | R46: =+MONTH(C46) | T46: 1027439 | AB46: Cerrada | AC46: =+VLOOKUP(T46,'BBDD ACREEDORES'!$B:$C,2,0) | AE46: =IF(AB46="Abierta",V46,"Cerrada")
B47: Cerrado | C47: 45092.658 | E47: [DISC_53616][P][SEN_[BP__][Abr23][L][V01]][5433421] | F47: 760103675 | G47: Generadora del Pacifico SpA | H47: 77316204 | I47: CGE COMERCIALIZADORA SPA | J47: Pago | K47: 147886 | L47: 147886 | M47: DISC_53616 | N47: 45098.328 | O47: Acreedor | P47: Pago | Q47: No | R47: =+MONTH(C47) | T47: 1008148 | AB47: Cerrada | AC47: =+VLOOKUP(T47,'BBDD ACREEDORES'!$B:$C,2,0) | AE47: =IF(AB47="Abierta",V47,"Cerrada")
B48: Cerrado | C48: 45092.658 | E48: [DISC_53617][P][SEN_[TEE_][Abr23][L][V01]][5466938] | F48: 760103675 | G48: Generadora del Pacifico SpA | H48: 77316204 | I48: CGE COMERCIALIZADORA SPA | J48: Pago | K48: 138297 | L48: 138297 | M48: DISC_53617 | N48: 45098.328 | O48: Acreedor | P48: Pago | Q48: No | R48: =+MONTH(C48) | T48: 1008148 | AB48: Cerrada | AC48: =+VLOOKUP(T48,'BBDD ACREEDORES'!$B:$C,2,0) | AE48: =IF(AB48="Abierta",V48,"Cerrada")
B49: Cerrado | C49: 45092.691 | E49: [DISC_53655][P][SEN_[BP__][Abr23][L][V01]][5433624] | F49: 764520556 | G49: Prime Energía Quickstart SpA | H49: 77316204 | I49: CGE COMERCIALIZADORA SPA | J49: Pago | K49: 710353 | L49: 710353 | M49: DISC_53655 | N49: 45098.361 | O49: Acreedor | P49: Pago | Q49: No | R49: =+MONTH(C49) | T49: 1026410 | AB49: Cerrada | AC49: =+VLOOKUP(T49,'BBDD ACREEDORES'!$B:$C,2,0) | AE49: =IF(AB49="Abierta",V49,"Cerrada")
B50: Cerrado | C50: 45092.691 | E50: [DISC_53656][P][SEN_[TEE_][Abr23][L][V01]][5467146] | F50: 764520556 | G50: Prime Energía Quickstart SpA | H50: 77316204 | I50: CGE COMERCIALIZADORA SPA | J50: Pago | K50: 103703 | L50: 103703 | M50: DISC_53656 | N50: 45098.361 | O50: Acreedor | P50: Pago | Q50: No | R50: =+MONTH(C50) | T50: 1026410 | AB50: Cerrada | AC50: =+VLOOKUP(T50,'BBDD ACREEDORES'!$B:$C,2,0) | AE50: =IF(AB50="Abierta",V50,"Cerrada")
B51: Cerrado | C51: 45093.459 | E51: [DISC_53779][P][SEN_[BP__][Abr23][L][V01]][5433274] | F51: 760441295 | G51: Alto Cautín SpA | H51: 77316204 | I51: CGE COMERCIALIZADORA SPA | J51: Pago | K51: 7487 | L51: 7487 | M51: DISC_53779 | N51: 45078 | O51: Acreedor | P51: Pago | Q51: No | R51: =+MONTH(C51) | T51: 1025979 | AB51: Cerrada | AC51: =+VLOOKUP(T51,'BBDD ACREEDORES'!$B:$C,2,0) | AE51: =IF(AB51="Abierta",V51,"Cerrada")
B52: Cerrado | C52: 45093.482 | E52: [DISC_53791][P][SEN_[TEE_][Abr23][L][V01]][5466911] | F52: 769258000 | G52: ESPINOS S.A. | H52: 77316204 | I52: CGE COMERCIALIZADORA SPA | J52: Pago | K52: 604896 | L52: 604896 | M52: DISC_53791 | N52: 45078 | O52: Acreedor | P52: Pago | Q52: No | R52: =+MONTH(C52) | T52: 1007707 | AB52: Cerrada | AC52: =+VLOOKUP(T52,'BBDD ACREEDORES'!$B:$C,2,0) | AE52: =IF(AB52="Abierta",V52,"Cerrada")
B53: Cerrado | C53: 45093.483 | E53: [DISC_53792][P][SEN_[BP__][Abr23][L][V01]][5433392] | F53: 769258000 | G53: ESPINOS S.A. | H53: 77316204 | I53: CGE COMERCIALIZADORA SPA | J53: Pago | K53: 331669 | L53: 331669 | M53: DISC_53792 | N53: 45078 | O53: Acreedor | P53: Pago | Q53: No | R53: =+MONTH(C53) | T53: 1007707 | AB53: Cerrada | AC53: =+VLOOKUP(T53,'BBDD ACREEDORES'!$B:$C,2,0) | AE53: =IF(AB53="Abierta",V53,"Cerrada")
A54: Espera - Cierre Anticipado - Seguimiento Acreedor - En Plazo de Regulación - Seguimiento Deudor - Espera Movimientos - CANCELAR | B54: Cerrado | C54: 45097.351 | D54: - Sin Asignar - Paola Ahumada - Usuario Pivot | E54: [DISC_54027][P][SEN_[TEE_][Abr23][L][V01]][5467179] | F54: 995287501 | G54: SOCIEDAD GENERADORA AUSTRAL S.A. | H54: 77316204 | I54: CGE COMERCIALIZADORA SPA | J54: Pago | K54: 1896679 | L54: 1593848 | M54: DISC_54027 | N54: 45082 | O54: Acreedor | P54: Pago | Q54: No | R54: =+MONTH(C54) | S54: =+C54+14 | T54: 1007708 | U54: 46815 | W54: Se paga el 7/7 | AB54: Cerrada | AC54: =+VLOOKUP(T54,'BBDD ACREEDORES'!$B:$C,2,0) | AE54: =IF(AB54="Abierta",V54,"Cerrada")
A55: Espera - Cierre Anticipado - Seguimiento Acreedor - En Plazo de Regulación - Seguimiento Deudor - Espera Movimientos - CANCELAR | B55: Cerrado | C55: 45097.452 | D55: - Sin Asignar - Paola Ahumada - Usuario Pivot | E55: [DISC_54057][P][SEN_[BP__][Abr23][L][V01]][5433657] | F55: 995287501 | G55: SOCIEDAD GENERADORA AUSTRAL S.A. | H55: 77316204 | I55: CGE COMERCIALIZADORA SPA | J55: Pago | K55: 80687 | L55: 67805 | M55: DISC_54057 | N55: 45082 | O55: Acreedor | P55: Pago | Q55: No | R55: =+MONTH(C55) | S55: =+C55+14 | T55: 1007708 | U55: 46865 | W55: Se paga el 7/7 | AB55: Cerrada | AC55: =+VLOOKUP(T55,'BBDD ACREEDORES'!$B:$C,2,0) | AE55: =IF(AB55="Abierta",V55,"Cerrada")
A56: Espera - Cierre Anticipado - Seguimiento Acreedor - En Plazo de Regulación - Seguimiento Deudor - Espera Movimientos - CANCELAR | B56: Cerrado | C56: 45097.634 | D56: - Sin Asignar - Paola Ahumada - Usuario Pivot | E56: [DISC_54307][P][SEN_[BP__][Abr23][L][V01]][5433390] | F56: 877565009 | G56: Enap Refinerias S.A. | H56: 77316204 | I56: CGE COMERCIALIZADORA SPA | J56: Pago | K56: 14869 | L56: 12495 | M56: DISC_54307 | N56: 45079 | O56: Acreedor | P56: Pago | Q56: No | R56: =+MONTH(C56) | S56: =+C56+14 | T56: 1008529 | U56: 652893 | W56: Se paga el 7/7 | AB56: Cerrada | AC56: =+VLOOKUP(T56,'BBDD ACREEDORES'!$B:$C,2,0) | AE56: =IF(AB56="Abierta",V56,"Cerrada")
A57: Espera - Cierre Anticipado - Seguimiento Acreedor - En Plazo de Regulación - Seguimiento Deudor - Espera Movimientos - CANCELAR | B57: Cerrado | C57: 45097.76 | D57: - Sin Asignar - Paola Ahumada - Usuario Pivot | E57: [DISC_54677][P][SEN_[TEE_][Abr23][L][V01]][5466803] | F57: 760685577 | G57: Sonnedix Parque Eólico El Arrayán SpA | H57: 77316204 | I57: CGE COMERCIALIZADORA SPA | J57: Pago | K57: 1849066 | L57: 1553837 | M57: DISC_54677 | N57: 45078 | O57: Acreedor | P57: Pago | Q57: No | R57: =+MONTH(C57) | S57: =+C57+14 | T57: 1017381 | U57: 13655 | W57: Pagado 16/6 | AB57: Cerrada | AC57: =+VLOOKUP(T57,'BBDD ACREEDORES'!$B:$C,2,0) | AE57: =IF(AB57="Abierta",V57,"Cerrada")
A58: Espera - Cierre Anticipado - Seguimiento Acreedor - En Plazo de Regulación - Seguimiento Deudor - Espera Movimientos - CANCELAR | B58: Cerrado | C58: 45097.84 | D58: - Sin Asignar - Paola Ahumada - Usuario Pivot | E58: [DISC_54829][P][SEN_[TEE_][Abr23][L][V01]][5466803] | F58: 760685577 | G58: Sonnedix Parque Eólico El Arrayán SpA | H58: 77316204 | I58: CGE COMERCIALIZADORA SPA | J58: Pago | K58: 1849066 | L58: 1553837 | M58: DISC_54829 | N58: 45078 | O58: Acreedor | P58: Pago | Q58: No | R58: =+MONTH(C58) | S58: =+C58+14 | T58: 1017381 | U58: 13655 | W58: Pagado 16/6 | AB58: Cerrada | AC58: =+VLOOKUP(T58,'BBDD ACREEDORES'!$B:$C,2,0) | AE58: =IF(AB58="Abierta",V58,"Cerrada")
A59: Espera - Cierre Anticipado - Seguimiento Acreedor - En Plazo de Regulación - Seguimiento Deudor - Espera Movimientos - CANCELAR | B59: Cerrado | C59: 45099.686 | D59: - Sin Asignar - Paola Ahumada - Usuario Pivot | E59: [DISC_55049][P][SEN_[TEE_][Abr23][L][V01]][5467061] | F59: 760456128 | G59: Electrica Nueva Energía S.A. | H59: 77316204 | I59: CGE COMERCIALIZADORA SPA | J59: Pago | K59: 882004 | L59: 741180 | M59: DISC_55049 | N59: 45078 | O59: Acreedor | P59: Pago | Q59: No | R59: =+MONTH(C59) | S59: =+C59+14 | T59: 1007717 | U59: 6832 | W59: Pagado 16/6 | AB59: Cerrada | AC59: =+VLOOKUP(T59,'BBDD ACREEDORES'!$B:$C,2,0) | AE59: =IF(AB59="Abierta",V59,"Cerrada")
A60: Espera - Cierre Anticipado - Seguimiento Acreedor - En Plazo de Regulación - Seguimiento Deudor - Espera Movimientos - CANCELAR | B60: Cerrado | C60: 45104.703 | D60: - Sin Asignar - Paola Ahumada - Usuario Pivot | E60: [DISC_55335][P][SEN_[BP__][Abr23][L][V01]][5433311] | F60: 765505801 | G60: Central Cardones S.A. | H60: 77316204 | I60: CGE COMERCIALIZADORA SPA | J60: Pago | K60: 222570 | L60: 187034 | M60: DISC_55335 | N60: 45078 | O60: Acreedor | P60: Pago | Q60: No | R60: =+MONTH(C60) | T60: 1010018 | U60: 11343 | W60: Pagado 16/6 | AB60: Cerrada | AC60: =+VLOOKUP(T60,'BBDD ACREEDORES'!$B:$C,2,0) | AE60: =IF(AB60="Abierta",V60,"Cerrada")
A61: Espera - Cierre Anticipado - Seguimiento Acreedor - En Plazo de Regulación - Seguimiento Deudor - Espera Movimientos - CANCELAR | B61: Cerrado | C61: 45104.703 | D61: - Sin Asignar - Paola Ahumada - Usuario Pivot | E61: [DISC_55336][P][SEN_[TEE_][Abr23][L][V01]][5467065] | F61: 760604410 | G61: Central Yungay S.A. | H61: 77316204 | I61: CGE COMERCIALIZADORA SPA | J61: Pago | K61: 1028342 | L61: 864153 | M61: DISC_55336 | N61: 45078 | O61: Acreedor | P61: Pago | Q61: No | R61: =+MONTH(C61) | S61: =+C61+14 | T61: 1015580 | U61: 24815 | W61: Pagado 16/6 | AB61: Cerrada | AC61: =+VLOOKUP(T61,'BBDD ACREEDORES'!$B:$C,2,0) | AE61: =IF(AB61="Abierta",V61,"Cerrada")
A62: Espera - Seguimiento Deudor - Cierre Anticipado - Seguimiento Acreedor - En Plazo de Regulación - Espera Movimientos - CANCELAR | B62: Cerrado | C62: 45105.726 | D62: - Sin Asignar - Usuario Pivot | E62: [DISC_55402][P][SEN_[CUN_][Dic22][L][V01]][5004506] | F62: 764103742 | G62: SISTEMA DE TRANSMISIÓN DEL NORTE S.A. | H62: 77316204 | I62: CGE COMERCIALIZADORA SPA | J62: Pago | K62: 111093 | L62: 93356 | M62: DISC_55402 | N62: 44966 | O62: Acreedor | P62: Pago | Q62: No | R62: =+MONTH(C62) | S62: =+C62+14 | T62: 1025221 | U62: 18862 | W62: Factura ingresada 5/7 | AB62: Cerrada | AC62: =+VLOOKUP(T62,'BBDD ACREEDORES'!$B:$C,2,0) | AE62: =IF(AB62="Abierta",V62,"Cerrada")
A63: Espera - Seguimiento Deudor - Cierre Anticipado - Seguimiento Acreedor - En Plazo de Regulación - Espera Movimientos - CANCELAR | B63: Cerrado | C63: 45105.759 | D63: - Sin Asignar - Usuario Pivot | E63: [DISC_55420][P][SEN_[TEE_][Abr23][L][V01]][5466878] | F63: 763827542 | G63: Energía Atacama S.A. | H63: 77316204 | I63: CGE COMERCIALIZADORA SPA | J63: Pago | K63: 18381 | L63: 15447 | M63: DISC_55420 | N63: 45086 | O63: Acreedor | P63: Pago | Q63: No | R63: =+MONTH(C63) | S63: =+C63+14 | T63: 1018350 | U63: 13336 | W63: Pagado 16/6 | AB63: Cerrada | AC63: =+VLOOKUP(T63,'BBDD ACREEDORES'!$B:$C,2,0) | AE63: =IF(AB63="Abierta",V63,"Cerrada")
A64: Espera - Seguimiento Deudor - Cierre Anticipado - Seguimiento Acreedor - En Plazo de Regulación - Espera Movimientos - CANCELAR | B64: Cerrado | C64: 45106.619 | D64: - Sin Asignar - Usuario Pivot | E64: [DISC_55523][P][SEN_[BP__][Abr23][L][V01]][5433672] | F64: 772577133 | G64: Sonnedix Energy Trading Chile SpA | H64: 77316204 | I64: CGE COMERCIALIZADORA SPA | J64: Pago | K64: 474 | L64: 399 | M64: DISC_55523 | N64: 45078 | O64: Acreedor | P64: Pago | Q64: No | R64: =+MONTH(C64) | S64: =+C64+14 | T64: 1026655 | U64: 2324 | W64: Pagado 16/6 | AB64: Cerrada | AC64: =+VLOOKUP(T64,'BBDD ACREEDORES'!$B:$C,2,0) | AE64: =IF(AB64="Abierta",V64,"Cerrada")
A65: Espera - Seguimiento Deudor - Cierre Anticipado - Seguimiento Acreedor - En Plazo de Regulación - Espera Movimientos - CANCELAR | B65: Cerrado | C65: 45111.42 | D65: - Sin Asignar - Usuario Pivot | E65: [DISC_56242][P][SEN_[TEE_][Abr23][R][V01]][5492204] | F65: 762021781 | G65: Ibereólica Cabo Leones II S.A. | H65: 77316204 | I65: CGE COMERCIALIZADORA SPA | J65: Pago | K65: 1136721 | L65: 955228 | M65: DISC_56242 | N65: 45099 | O65: Acreedor | P65: Pago | Q65: No | R65: =+MONTH(C65) | S65: =+C65+14 | T65: 1025180 | U65: 2857 | W65: 41846817 1002962010 | AB65: Cerrada | AC65: =+VLOOKUP(T65,'BBDD ACREEDORES'!$B:$C,2,0) | AE65: =IF(AB65="Abierta",V65,"Cerrada")
A66: Espera - Cierre Anticipado - Seguimiento Acreedor - En Plazo de Regulación - Seguimiento Deudor - Espera Movimientos - CANCELAR | B66: Cerrado | C66: 45112.69 | D66: - Sin Asignar - Usuario Pivot | E66: [DISC_56426][P][SEN_[CUN_][Abr23][L][V01]][5546643] | F66: 767876904 | G66: Transmisora Eléctrica del Norte S.A. | H66: 77316204 | I66: CGE COMERCIALIZADORA SPA | J66: Pago | K66: 3829210 | L66: 3217824 | M66: DISC_56426 | N66: 45090 | O66: Acreedor | P66: Pago | Q66: No | R66: =+MONTH(C66) | S66: =+C66+14 | T66: 1024418 | U66: 11440 | W66: 41846384 1002961306 | AB66: Cerrada | AC66: =+VLOOKUP(T66,'BBDD ACREEDORES'!$B:$C,2,0) | AE66: =IF(AB66="Abierta",V66,"Cerrada")
A67: Espera - Seguimiento Deudor - Cierre Anticipado - Seguimiento Acreedor - En Plazo de Regulación - Espera Movimientos - CANCELAR | B67: Cerrado | C67: 45117.615 | D67: - Sin Asignar - Usuario Pivot | E67: [DISC_58138][P][SEN_[TEE_][Abr23][L][V01]][5466909] | F67: 877565009 | G67: Enap Refinerias S.A. | H67: 77316204 | I67: CGE COMERCIALIZADORA SPA | J67: Pago | K67: 981066 | L67: 824426 | M67: DISC_58138 | N67: 45079 | O67: Acreedor | P67: Pago | Q67: No | R67: =+MONTH(C67) | S67: 45131 | T67: 1008529 | U67: 652769 | W67: 41843970 1002957727 | AB67: Cerrada | AC67: =+VLOOKUP(T67,'BBDD ACREEDORES'!$B:$C,2,0) | AE67: =IF(AB67="Abierta",V67,"Cerrada")
A68: Espera - Seguimiento Deudor - Cierre Anticipado - Seguimiento Acreedor - En Plazo de Regulación - Espera Movimientos - CANCELAR | B68: Cerrado | C68: 45117.636 | D68: - Sin Asignar - Usuario Pivot | E68: [DISC_58160][P][SEN_[TEE_][May23][L][V01]][5665458] | F68: 760718912 | G68: Hidroelectrica Allipén S.A. | H68: 77316204 | I68: CGE COMERCIALIZADORA SPA | J68: Pago | K68: 107695 | L68: 90500 | M68: DISC_58160 | N68: 45121.305 | O68: Acreedor | P68: Pago | Q68: No | R68: =+MONTH(C68) | S68: 45131 | T68: 1015404 | U68: 12062 | W68: 41851070 1002969093 | AB68: Cerrada | AC68: =+VLOOKUP(T68,'BBDD ACREEDORES'!$B:$C,2,0) | AE68: =IF(AB68="Abierta",V68,"Cerrada")
A69: Espera - Seguimiento Deudor - Cierre Anticipado - Seguimiento Acreedor - En Plazo de Regulación - Espera Movimientos - CANCELAR | B69: Cerrado | C69: 45117.636 | D69: - Sin Asignar - Usuario Pivot | E69: [DISC_58161][P][SEN_[BP__][May23][L][V01]][5562170] | F69: 760718912 | G69: Hidroelectrica Allipén S.A. | H69: 77316204 | I69: CGE COMERCIALIZADORA SPA | J69: Pago | K69: 2732 | L69: 2296 | M69: DISC_58161 | N69: 45121.305 | O69: Acreedor | P69: Pago | Q69: No | R69: =+MONTH(C69) | S69: 45131 | T69: 1015404 | U69: 12120 | W69: w | AB69: Cerrada | AC69: =+VLOOKUP(T69,'BBDD ACREEDORES'!$B:$C,2,0) | AE69: =IF(AB69="Abierta",V69,"Cerrada")
A70: Espera - Seguimiento Deudor - Cierre Anticipado - Seguimiento Acreedor - En Plazo de Regulación - Espera Movimientos - CANCELAR | B70: Cerrado | C70: 45117.669 | D70: - Sin Asignar - Usuario Pivot | E70: [DISC_58253][P][SEN_[TEE_][May23][L][V01]][5665812] | F70: 761892746 | G70: Hidroeléctrica Río Colorado S.A. | H70: 77316204 | I70: CGE COMERCIALIZADORA SPA | J70: Pago | K70: 38296 | L70: 32182 | M70: DISC_58253 | N70: 45121.338 | O70: Acreedor | P70: Pago | Q70: No | R70: =+MONTH(C70) | S70: 45131 | T70: 1023458 | U70: 15247 | W70: 41851178 1002969198 | AB70: Cerrada | AC70: =+VLOOKUP(T70,'BBDD ACREEDORES'!$B:$C,2,0) | AE70: =IF(AB70="Abierta",V70,"Cerrada")
A71: Espera - Seguimiento Deudor - Cierre Anticipado - Seguimiento Acreedor - En Plazo de Regulación - Espera Movimientos - CANCELAR | B71: Cerrado | C71: 45117.669 | D71: - Sin Asignar - Usuario Pivot | E71: [DISC_58254][P][SEN_[BP__][May23][L][V01]][5562531] | F71: 761892746 | G71: Hidroeléctrica Río Colorado S.A. | H71: 77316204 | I71: CGE COMERCIALIZADORA SPA | J71: Pago | K71: 1223 | L71: 1028 | M71: DISC_58254 | N71: 45121.339 | O71: Acreedor | P71: Pago | Q71: No | R71: =+MONTH(C71) | S71: 45131 | T71: 1023458 | U71: 15299 | W71: 41850110 1002970219 | AB71: Cerrada | AC71: =+VLOOKUP(T71,'BBDD ACREEDORES'!$B:$C,2,0) | AE71: =IF(AB71="Abierta",V71,"Cerrada")
A72: Espera - Cierre Anticipado - Seguimiento Acreedor - En Plazo de Regulación - Seguimiento Deudor - Espera Movimientos - CANCELAR | B72: Cerrado | C72: 45118.385 | D72: - Sin Asignar - Usuario Pivot | E72: [DISC_58614][P][SEN_[TEE_][Abr23][L][V01]][5467082] | F72: 767955189 | G72: PARQUE SOLAR H6 | H72: 77316204 | I72: CGE COMERCIALIZADORA SPA | J72: Pago | K72: 23617 | L72: 19847 | M72: DISC_58614 | N72: 45124.055 | O72: Acreedor | P72: Pago | Q72: No | R72: =+MONTH(C72) | S72: 45132 | T72: 1025825 | U72: 6088 | W72: 41844235 1002957991 | AB72: Cerrada | AC72: =+VLOOKUP(T72,'BBDD ACREEDORES'!$B:$C,2,0) | AE72: =IF(AB72="Abierta",V72,"Cerrada")
A73: Espera - Cierre Anticipado - Seguimiento Acreedor - En Plazo de Regulación - Seguimiento Deudor - Espera Movimientos - CANCELAR | B73: Cerrado | C73: 45118.388 | D73: - Sin Asignar - Usuario Pivot | E73: [DISC_58619][P][SEN_[BP__][Abr23][L][V01]][5433558] | F73: 767955189 | G73: PARQUE SOLAR H6 | H73: 77316204 | I73: CGE COMERCIALIZADORA SPA | J73: Pago | K73: 924 | L73: 777 | M73: DISC_58619 | N73: 45124.057 | O73: Acreedor | P73: Pago | Q73: No | R73: =+MONTH(C73) | S73: 45132 | T73: 1025825 | U73: 6126 | W73: 41843737 1002957430 | AB73: Cerrada | AC73: =+VLOOKUP(T73,'BBDD ACREEDORES'!$B:$C,2,0) | AE73: =IF(AB73="Abierta",V73,"Cerrada")
A74: Espera - Seguimiento Deudor - Cierre Anticipado - Seguimiento Acreedor - En Plazo de Regulación - Espera Movimientos - CANCELAR | B74: Cerrado | C74: 45118.455 | D74: - Sin Asignar - Usuario Pivot | E74: [DISC_58635][P][SEN_[BP__][May23][L][V01]][5562269] | F74: 762640252 | G74: Hidroeléctrica Embalse Ancoa SpA | H74: 77316204 | I74: CGE COMERCIALIZADORA SPA | J74: Pago | K74: 7395 | L74: 6215 | M74: DISC_58635 | N74: 45124.124 | O74: Acreedor | P74: Pago | Q74: No | R74: =+MONTH(C74) | S74: 45132 | T74: 1023872 | U74: 14564 | W74: 41849932 1002970041 | AB74: Cerrada | AC74: =+VLOOKUP(T74,'BBDD ACREEDORES'!$B:$C,2,0) | AE74: =IF(AB74="Abierta",V74,"Cerrada")
A75: Espera - Seguimiento Deudor - Cierre Anticipado - Seguimiento Acreedor - En Plazo de Regulación - Espera Movimientos - CANCELAR | B75: Cerrado | C75: 45118.545 | D75: - Sin Asignar - Usuario Pivot | E75: [DISC_58746][P][SEN_[BP__][May23][L][V01]][5562530] | F75: 760711136 | G75: Hidroeléctrica Río Huasco S.A. | H75: 77316204 | I75: CGE COMERCIALIZADORA SPA | J75: Pago | K75: 6341 | L75: 5329 | M75: DISC_58746 | N75: 45124.215 | O75: Acreedor | P75: Pago | Q75: No | R75: =+MONTH(C75) | S75: 45132 | T75: 1016827 | U75: 15566 | W75: 41849937 1002970046 | AB75: Cerrada | AC75: =+VLOOKUP(T75,'BBDD ACREEDORES'!$B:$C,2,0) | AE75: =IF(AB75="Abierta",V75,"Cerrada")
A76: Espera - Seguimiento Deudor - Cierre Anticipado - Seguimiento Acreedor - En Plazo de Regulación - Espera Movimientos - CANCELAR | B76: Cerrado | C76: 45118.546 | D76: - Sin Asignar - Usuario Pivot | E76: [DISC_58747][P][SEN_[TEE_][May23][L][V01]][5665811] | F76: 760711136 | G76: Hidroeléctrica Río Huasco S.A. | H76: 77316204 | I76: CGE COMERCIALIZADORA SPA | J76: Pago | K76: 40480 | L76: 34017 | M76: DISC_58747 | N76: 45124.215 | O76: Acreedor | P76: Pago | Q76: No | R76: =+MONTH(C76) | S76: 45132 | T76: 1016827 | U76: 15643 | W76: 41851172 1002969192 | AB76: Cerrada | AC76: =+VLOOKUP(T76,'BBDD ACREEDORES'!$B:$C,2,0) | AE76: =IF(AB76="Abierta",V76,"Cerrada")
A77: Espera - Seguimiento Deudor - Cierre Anticipado - Seguimiento Acreedor - En Plazo de Regulación - Espera Movimientos - CANCELAR | B77: Cerrado | C77: 45118.689 | D77: - Sin Asignar - Usuario Pivot | E77: [DISC_58868][P][SEN_[BP__][May23][L][V01]][5562206] | F77: 765505801 | G77: Central Cardones S.A. | H77: 77316204 | I77: CGE COMERCIALIZADORA SPA | J77: Pago | K77: 221851 | L77: 186430 | M77: DISC_58868 | N77: 45111 | O77: Acreedor | P77: Pago | Q77: No | R77: =+MONTH(C77) | S77: 45132 | T77: 1010018 | U77: 11399 | W77: 41849847 1002969956 | AB77: Cerrada | AC77: =+VLOOKUP(T77,'BBDD ACREEDORES'!$B:$C,2,0) | AE77: =IF(AB77="Abierta",V77,"Cerrada")
A78: Espera - Seguimiento Deudor - Cierre Anticipado - Seguimiento Acreedor - En Plazo de Regulación - Espera Movimientos - CANCELAR | B78: Cerrado | C78: 45118.698 | D78: - Sin Asignar - Usuario Pivot | E78: [DISC_59028][P][SEN_[TEE_][May23][L][V01]][5665520] | F78: 763269493 | G78: Central Colmito S.A. | H78: 77316204 | I78: CGE COMERCIALIZADORA SPA | J78: Pago | K78: 2848767 | L78: 2393922 | M78: DISC_59028 | N78: 45111 | O78: Acreedor | P78: Pago | Q78: No | R78: =+MONTH(C78) | S78: 45132 | T78: 1020453 | U78: 10065 | W78: 41850976 1002969003 | AB78: Cerrada | AC78: =+VLOOKUP(T78,'BBDD ACREEDORES'!$B:$C,2,0) | AE78: =IF(AB78="Abierta",V78,"Cerrada")
A79: Espera - Cierre Anticipado - Seguimiento Acreedor - En Plazo de Regulación - Seguimiento Deudor - Espera Movimientos - CANCELAR | B79: Cerrado | C79: 45119.576 | D79: - Sin Asignar - Usuario Pivot | E79: [DISC_60413][P][SEN_[BP__][May23][L][V01]][5562228] | F79: 763269493 | G79: Central Colmito S.A. | H79: 77316204 | I79: CGE COMERCIALIZADORA SPA | J79: Pago | K79: 75442 | L79: 63397 | M79: DISC_60413 | N79: 45111 | O79: Acreedor | P79: Pago | Q79: No | R79: =+MONTH(C79) | S79: 45133 | T79: 1020453 | U79: 10009 | W79: Pagado 4/8 | AB79: Cerrada | AC79: =+VLOOKUP(T79,'BBDD ACREEDORES'!$B:$C,2,0) | AE79: =IF(AB79="Abierta",V79,"Cerrada")
A80: Espera - Seguimiento Deudor - Cierre Anticipado - Seguimiento Acreedor - En Plazo de Regulación - Espera Movimientos - CANCELAR | B80: Cerrado | C80: 45119.582 | D80: - Sin Asignar - Usuario Pivot | E80: [DISC_60570][P][SEN_[BP__][May23][L][V01]][5562438] | F80: 760604410 | G80: Central Yungay S.A. | H80: 77316204 | I80: CGE COMERCIALIZADORA SPA | J80: Pago | K80: 231792 | L80: 194784 | M80: DISC_60570 | N80: 45111 | O80: Acreedor | P80: Pago | Q80: No | R80: =+MONTH(C80) | S80: 45133 | T80: 1015580 | U80: 24883 | W80: 41849845 1002969955 | AB80: Cerrada | AC80: =+VLOOKUP(T80,'BBDD ACREEDORES'!$B:$C,2,0) | AE80: =IF(AB80="Abierta",V80,"Cerrada")
A81: Espera - Seguimiento Deudor - Cierre Anticipado - Seguimiento Acreedor - En Plazo de Regulación - Espera Movimientos - CANCELAR | B81: Cerrado | C81: 45119.592 | D81: - Sin Asignar - Usuario Pivot | E81: [DISC_60921][P][SEN_[TEE_][May23][L][V01]][5665718] | F81: 760604410 | G81: Central Yungay S.A. | H81: 77316204 | I81: CGE COMERCIALIZADORA SPA | J81: Pago | K81: 445656 | L81: 374501 | M81: DISC_60921 | N81: 45111 | O81: Acreedor | P81: Pago | Q81: No | R81: =+MONTH(C81) | S81: 45133 | T81: 1015580 | U81: 24952 | W81: 41851009 1002969035 | AB81: Cerrada | AC81: =+VLOOKUP(T81,'BBDD ACREEDORES'!$B:$C,2,0) | AE81: =IF(AB81="Abierta",V81,"Cerrada")
A82: Espera - Seguimiento Deudor - Cierre Anticipado - Seguimiento Acreedor - En Plazo de Regulación - Espera Movimientos - CANCELAR | B82: Cerrado | C82: 45120.492 | D82: - Sin Asignar - Usuario Pivot | E82: [DISC_61331][P][SEN_[TEE_][May23][L][V01]][5665692] | F82: 760551368 | G82: Hidroeléctrica Mallarauco S.A. | H82: 77316204 | I82: CGE COMERCIALIZADORA SPA | J82: Pago | K82: 61152 | L82: 51389 | M82: DISC_61331 | N82: 45126.162 | O82: Acreedor | P82: Pago | Q82: No | R82: =+MONTH(C82) | S82: 45133 | T82: 1021439 | U82: 10828 | W82: 41851130 1002969151 | AB82: Cerrada | AC82: =+VLOOKUP(T82,'BBDD ACREEDORES'!$B:$C,2,0) | AE82: =IF(AB82="Abierta",V82,"Cerrada")
A83: Espera - Seguimiento Deudor - Cierre Anticipado - Seguimiento Acreedor - En Plazo de Regulación - Espera Movimientos - CANCELAR | B83: Cerrado | C83: 45120.493 | D83: - Sin Asignar - Usuario Pivot | E83: [DISC_61332][P][SEN_[BP__][May23][L][V01]][5562413] | F83: 760551368 | G83: Hidroeléctrica Mallarauco S.A. | H83: 77316204 | I83: CGE COMERCIALIZADORA SPA | J83: Pago | K83: 3768 | L83: 3167 | M83: DISC_61332 | N83: 45126.162 | O83: Acreedor | P83: Pago | Q83: No | R83: =+MONTH(C83) | S83: 45133 | T83: 1021439 | U83: 10880 | W83: 41849975 1002970085 | AB83: Cerrada | AC83: =+VLOOKUP(T83,'BBDD ACREEDORES'!$B:$C,2,0) | AE83: =IF(AB83="Abierta",V83,"Cerrada")
A84: Espera - Seguimiento Deudor - Cierre Anticipado - Seguimiento Acreedor - En Plazo de Regulación - Espera Movimientos - CANCELAR | B84: Cerrado | C84: 45120.532 | D84: - Sin Asignar - Usuario Pivot | E84: [DISC_61373][P][SEN_[BP__][May23][L][V01]][5562502] | F84: 995896206 | G84: Hidroelectrica Puclaro S.A. | H84: 77316204 | I84: CGE COMERCIALIZADORA SPA | J84: Pago | K84: 6235 | L84: 5240 | M84: DISC_61373 | N84: 45126.202 | O84: Acreedor | P84: Pago | Q84: No | R84: =+MONTH(C84) | S84: 45133 | T84: 1014010 | U84: 12608 | W84: 41849938 1002970047 | AB84: Cerrada | AC84: =+VLOOKUP(T84,'BBDD ACREEDORES'!$B:$C,2,0) | AE84: =IF(AB84="Abierta",V84,"Cerrada")
A85: Espera - Seguimiento Deudor - Cierre Anticipado - Seguimiento Acreedor - En Plazo de Regulación - Espera Movimientos - CANCELAR | B85: Cerrado | C85: 45120.533 | D85: - Sin Asignar - Usuario Pivot | E85: [DISC_61377][P][SEN_[TEE_][May23][L][V01]][5665784] | F85: 995896206 | G85: Hidroelectrica Puclaro S.A. | H85: 77316204 | I85: CGE COMERCIALIZADORA SPA | J85: Pago | K85: 19130 | L85: 16076 | M85: DISC_61377 | N85: 45126.202 | O85: Acreedor | P85: Pago | Q85: No | R85: =+MONTH(C85) | S85: 45133 | T85: 1014010 | U85: 12684 | W85: 41851288 1002969308 | AB85: Cerrada | AC85: =+VLOOKUP(T85,'BBDD ACREEDORES'!$B:$C,2,0) | AE85: =IF(AB85="Abierta",V85,"Cerrada")
A86: Espera - Seguimiento Deudor - Cierre Anticipado - Seguimiento Acreedor - En Plazo de Regulación - Espera Movimientos - CANCELAR | B86: Cerrado | C86: 45120.669 | D86: - Sin Asignar - Usuario Pivot | E86: [DISC_61443][P][SEN_[TEE_][May23][L][V01]][5665565] | F86: 760093289 | G86: Enlasa Generación Chile S.A. | H86: 77316204 | I86: CGE COMERCIALIZADORA SPA | J86: Pago | K86: 678370 | L86: 570059 | M86: DISC_61443 | N86: 45111 | O86: Acreedor | P86: Pago | Q86: No | R86: =+MONTH(C86) | S86: 45133 | T86: 1007718 | U86: 5595 | W86: 41850998 1002969024 | AB86: Cerrada | AC86: =+VLOOKUP(T86,'BBDD ACREEDORES'!$B:$C,2,0) | AE86: =IF(AB86="Abierta",V86,"Cerrada")
A87: Espera - Seguimiento Deudor - Cierre Anticipado - Seguimiento Acreedor - En Plazo de Regulación - Espera Movimientos - CANCELAR | B87: Cerrado | C87: 45120.741 | D87: - Sin Asignar - Usuario Pivot | E87: [DISC_61474][P][SEN_[BP__][May23][L][V01]][5562280] | F87: 760093289 | G87: Enlasa Generación Chile S.A. | H87: 77316204 | I87: CGE COMERCIALIZADORA SPA | J87: Pago | K87: 386259 | L87: 324588 | M87: DISC_61474 | N87: 45111 | O87: Acreedor | P87: Pago | Q87: No | R87: =+MONTH(C87) | S87: 45133 | T87: 1007718 | U87: 5671 | W87: 41849841 1002969951 | AB87: Cerrada | AC87: =+VLOOKUP(T87,'BBDD ACREEDORES'!$B:$C,2,0) | AE87: =IF(AB87="Abierta",V87,"Cerrada")
A88: Espera - Seguimiento Deudor - Cierre Anticipado - Seguimiento Acreedor - En Plazo de Regulación - Espera Movimientos - CANCELAR | B88: Cerrado | C88: 45120.752 | D88: - Sin Asignar - Usuario Pivot | E88: [DISC_61498][P][SEN_[SCRT][May23][L][V01]][5657423] | F88: 760093289 | G88: Enlasa Generación Chile S.A. | H88: 77316204 | I88: CGE COMERCIALIZADORA SPA | J88: Pago | K88: 278994 | L88: 234449 | M88: DISC_61498 | N88: 45111 | O88: Acreedor | P88: Pago | Q88: No | R88: =+MONTH(C88) | S88: 45133 | T88: 1007718 | U88: 5723 | W88: 41850434 1002967645 | AB88: Cerrada | AC88: =+VLOOKUP(T88,'BBDD ACREEDORES'!$B:$C,2,0) | AE88: =IF(AB88="Abierta",V88,"Cerrada")
A89: Espera - Seguimiento Deudor - Cierre Anticipado - Seguimiento Acreedor - En Plazo de Regulación - Espera Movimientos - CANCELAR | B89: Cerrado | C89: 45121.449 | D89: - Sin Asignar - Usuario Pivot | E89: [DISC_61612][P][SEN_[BP__][May23][L][V01]][5562347] | F89: 76025973k | G89: Hidroeléctrica Río Lircay S.A. | H89: 77316204 | I89: CGE COMERCIALIZADORA SPA | J89: Pago | K89: 27759 | L89: 23327 | M89: DISC_61612 | N89: 45111 | O89: Acreedor | P89: Pago | Q89: No | R89: =+MONTH(C89) | S89: 45134 | T89: 1013571 | U89: 18905 | W89: 41849885 1002969994 | AB89: Cerrada | AC89: =+VLOOKUP(T89,'BBDD ACREEDORES'!$B:$C,2,0) | AE89: =IF(AB89="Abierta",V89,"Cerrada")
A90: Espera - Seguimiento Deudor - Cierre Anticipado - Seguimiento Acreedor - En Plazo de Regulación - Espera Movimientos - CANCELAR | B90: Cerrado | C90: 45121.449 | D90: - Sin Asignar - Usuario Pivot | E90: [DISC_61613][P][SEN_[SCRT][May23][L][V01]][5657426] | F90: 76025973k | G90: Hidroeléctrica Río Lircay S.A. | H90: 77316204 | I90: CGE COMERCIALIZADORA SPA | J90: Pago | K90: 1950 | L90: 1639 | M90: DISC_61613 | N90: 45111 | O90: Acreedor | P90: Pago | Q90: No | R90: =+MONTH(C90) | S90: 45134 | T90: 1013571 | U90: 18955 | W90: 41850436 1002967647 | AB90: Cerrada | AC90: =+VLOOKUP(T90,'BBDD ACREEDORES'!$B:$C,2,0) | AE90: =IF(AB90="Abierta",V90,"Cerrada")
A91: Espera - Seguimiento Deudor - Cierre Anticipado - Seguimiento Acreedor - En Plazo de Regulación - Espera Movimientos - CANCELAR | B91: Cerrado | C91: 45121.449 | D91: - Sin Asignar - Usuario Pivot | E91: [DISC_61615][P][SEN_[TEE_][May23][L][V01]][5665630] | F91: 76025973k | G91: Hidroeléctrica Río Lircay S.A. | H91: 77316204 | I91: CGE COMERCIALIZADORA SPA | J91: Pago | K91: 364043 | L91: 305919 | M91: DISC_61615 | N91: 45111 | O91: Acreedor | P91: Pago | Q91: No | R91: =+MONTH(C91) | S91: 45134 | T91: 1013571 | U91: 19020 | W91: 41851017 1002969042 | AB91: Cerrada | AC91: =+VLOOKUP(T91,'BBDD ACREEDORES'!$B:$C,2,0) | AE91: =IF(AB91="Abierta",V91,"Cerrada")
A92: Espera - Seguimiento Deudor - Cierre Anticipado - Seguimiento Acreedor - En Plazo de Regulación - Espera Movimientos - CANCELAR | B92: Cerrado | C92: 45121.496 | D92: - Sin Asignar - Reinaldo Leyton - Usuario Pivot | E92: [DISC_61676][P][SEN_[BP__][May23][L][V01]][5562268] | F92: 765946603 | G92: Elektra Generación S.A. | H92: 77316204 | I92: CGE COMERCIALIZADORA SPA | J92: Pago | K92: 55669 | L92: 46781 | M92: DISC_61676 | N92: 45110 | O92: Acreedor | P92: Pago | Q92: No | R92: =+MONTH(C92) | S92: 45134 | T92: 1007706 | U92: 23070 | W92: 41849868 1002969977 | AB92: Cerrada | AC92: =+VLOOKUP(T92,'BBDD ACREEDORES'!$B:$C,2,0) | AE92: =IF(AB92="Abierta",V92,"Cerrada")
A93: Espera - Cierre Anticipado - Seguimiento Acreedor - En Plazo de Regulación - Seguimiento Deudor - Espera Movimientos - CANCELAR | B93: Cerrado | C93: 45124.723 | D93: - Sin Asignar - Paola Ahumada - Usuario Pivot | E93: [DISC_61954][P][SEN_[BP__][Abr23][L][V01]][5433412] | F93: 762130459 | G93: Fotovoltaica Norte Grande 5 SpA | H93: 77316204 | I93: CGE COMERCIALIZADORA SPA | J93: Pago | K93: 27191 | L93: 22850 | M93: DISC_61954 | N93: 45128.392 | O93: Acreedor | P93: Pago | Q93: No | R93: =+MONTH(C93) | S93: 45139 | T93: 1023433 | W93: Pagado 21/7 | AB93: Cerrada | AC93: =+VLOOKUP(T93,'BBDD ACREEDORES'!$B:$C,2,0) | AE93: =IF(AB93="Abierta",V93,"Cerrada")
A94: Espera - Seguimiento Deudor - Cierre Anticipado - Seguimiento Acreedor - En Plazo de Regulación - Espera Movimientos - CANCELAR | B94: Cerrado | C94: 45124.723 | D94: - Sin Asignar - Usuario Pivot | E94: [DISC_61955][P][SEN_[TEE_][Abr23][L][V01]][5466933] | F94: 762130459 | G94: Fotovoltaica Norte Grande 5 SpA | H94: 77316204 | I94: CGE COMERCIALIZADORA SPA | J94: Pago | K94: 237438 | L94: 199528 | M94: DISC_61955 | N94: 45128.393 | O94: Acreedor | P94: Pago | Q94: No | R94: =+MONTH(C94) | S94: 45139 | T94: 1023433 | W94: Pagado 21/7 | AB94: Cerrada | AC94: =+VLOOKUP(T94,'BBDD ACREEDORES'!$B:$C,2,0) | AE94: =IF(AB94="Abierta",V94,"Cerrada")
A95: Espera - Cierre Anticipado - Seguimiento Acreedor - En Plazo de Regulación - Seguimiento Deudor - Espera Movimientos - CANCELAR | B95: Cerrado | C95: 45125.703 | D95: - Sin Asignar - Usuario Pivot | E95: [DISC_62096][P][SEN_[BP__][May23][L][V01]][5562267] | F95: 770533120 | G95: ELECTRICA PINARES LTDA | H95: 77316204 | I95: CGE COMERCIALIZADORA SPA | J95: Pago | K95: 11195 | L95: 9408 | M95: DISC_62096 | N95: 45111 | O95: Acreedor | P95: Pago | Q95: No | R95: =+MONTH(C95) | S95: 45140 | T95: 1026485 | W95: Pagado 21/7 | AB95: Cerrada | AC95: =+VLOOKUP(T95,'BBDD ACREEDORES'!$B:$C,2,0) | AE95: =IF(AB95="Abierta",V95,"Cerrada")
A96: Espera - Cierre Anticipado - Seguimiento Acreedor - En Plazo de Regulación - Seguimiento Deudor - Espera Movimientos - CANCELAR | B96: Cerrado | C96: 45125.927 | D96: - Sin Asignar - Usuario Pivot | E96: [DISC_62125][P][SEN_[TEE_][May23][L][V01]][5665555] | F96: 770533120 | G96: ELECTRICA PINARES LTDA | H96: 77316204 | I96: CGE COMERCIALIZADORA SPA | J96: Pago | K96: 523 | L96: 440 | M96: DISC_62125 | N96: 45111 | O96: Acreedor | P96: Pago | Q96: No | R96: =+MONTH(C96) | S96: 45140 | T96: 1026485 | W96: Pagado 21/7 | AB96: Cerrada | AC96: =+VLOOKUP(T96,'BBDD ACREEDORES'!$B:$C,2,0) | AE96: =IF(AB96="Abierta",V96,"Cerrada")
A97: Espera - Seguimiento Deudor - Cierre Anticipado - Seguimiento Acreedor - En Plazo de Regulación - Espera Movimientos - CANCELAR | B97: Cerrado | C97: 45126.445 | D97: - Sin Asignar - Usuario Pivot | E97: [DISC_62151][P][SEN_[CUN_][Dic22][L][V01]][5004507] | F97: 773122016 | G97: Sistema de Transmisión del Sur S.A. | H97: 77316204 | I97: CGE COMERCIALIZADORA SPA | J97: Pago | K97: 213981 | L97: 179816 | M97: DISC_62151 | N97: 44966 | O97: Acreedor | P97: Pago | Q97: No | R97: =+MONTH(C97) | S97: 45141 | T97: 1006425 | W97: Pagado 21/7 | AB97: Cerrada | AC97: =+VLOOKUP(T97,'BBDD ACREEDORES'!$B:$C,2,0) | AE97: =IF(AB97="Abierta",V97,"Cerrada")
A98: Espera - Seguimiento Deudor - Cierre Anticipado - Seguimiento Acreedor - En Plazo de Regulación - Espera Movimientos - CANCELAR | B98: Cerrado | C98: 45126.467 | D98: - Sin Asignar - Usuario Pivot | E98: [DISC_62168][P][SEN_[ITE_][Abr23][L][V01]][5458100] | F98: 773122016 | G98: Sistema de Transmisión del Sur S.A. | H98: 77316204 | I98: CGE COMERCIALIZADORA SPA | J98: Pago | K98: 104224 | L98: 87584 | M98: DISC_62168 | N98: 45079 | O98: Acreedor | P98: Pago | Q98: No | R98: =+MONTH(C98) | S98: 45141 | T98: 1006425 | W98: Pagado 21/7 | AB98: Cerrada | AC98: =+VLOOKUP(T98,'BBDD ACREEDORES'!$B:$C,2,0) | AE98: =IF(AB98="Abierta",V98,"Cerrada")
A99: Espera - Seguimiento Deudor - Cierre Anticipado - Seguimiento Acreedor - En Plazo de Regulación - Espera Movimientos - CANCELAR | B99: Cerrado | C99: 45126.485 | D99: - Sin Asignar - Usuario Pivot | E99: [DISC_62180][P][SEN_[TEE_][May23][L][V01]][5665628] | F99: 768340005 | G99: Hidroelectrica Trueno S.A. | H99: 77316204 | I99: CGE COMERCIALIZADORA SPA | J99: Pago | K99: 32670 | L99: 27454 | M99: DISC_62180 | N99: 45132.155 | O99: Acreedor | P99: Pago | Q99: No | R99: =+MONTH(C99) | S99: 45141 | T99: 1026449 | AB99: Cerrada | AC99: =+VLOOKUP(T99,'BBDD ACREEDORES'!$B:$C,2,0) | AE99: =IF(AB99="Abierta",V99,"Cerrada")
A100: Espera - Seguimiento Deudor - Cierre Anticipado - Seguimiento Acreedor - En Plazo de Regulación - Espera Movimientos - CANCELAR | B100: Cerrado | C100: 45126.486 | D100: - Sin Asignar - Usuario Pivot | E100: [DISC_62181][P][SEN_[BP__][May23][L][V01]][5562342] | F100: 768340005 | G100: Hidroelectrica Trueno S.A. | H100: 77316204 | I100: CGE COMERCIALIZADORA SPA | J100: Pago | K100: 1730 | L100: 1454 | M100: DISC_62181 | N100: 45132.155 | O100: Acreedor | P100: Pago | Q100: No | R100: =+MONTH(C100) | S100: 45141 | T100: 1026449 | AB100: Cerrada | AC100: =+VLOOKUP(T100,'BBDD ACREEDORES'!$B:$C,2,0) | AE100: =IF(AB100="Abierta",V100,"Cerrada")
A101: Espera - Seguimiento Deudor - Cierre Anticipado - Seguimiento Acreedor - En Plazo de Regulación - Espera Movimientos - CANCELAR | B101: Cerrado | C101: 45126.488 | D101: - Sin Asignar - Usuario Pivot | E101: [DISC_62184][P][SEN_[ITP_][Dic22][L][V01]][4882556] | F101: 773122016 | G101: Sistema de Transmisión del Sur S.A. | H101: 77316204 | I101: CGE COMERCIALIZADORA SPA | J101: Pago | K101: 11065 | L101: 9299 | M101: DISC_62184 | N101: 45084 | O101: Acreedor | P101: Pago | Q101: No | R101: =+MONTH(C101) | S101: 45141 | T101: 1006425 | W101: Pagado 21/7 | AB101: Cerrada | AC101: =+VLOOKUP(T101,'BBDD ACREEDORES'!$B:$C,2,0) | AE101: =IF(AB101="Abierta",V101,"Cerrada")
A102: Espera - Seguimiento Deudor - Cierre Anticipado - Seguimiento Acreedor - En Plazo de Regulación - Espera Movimientos - CANCELAR | B102: Cerrado | C102: 45126.662 | D102: - Sin Asignar - Sebastián Parra - Usuario Pivot | E102: [DISC_62246][P][SEN_[BP__][May23][L][V01]][5562171] | F102: 760441295 | G102: Alto Cautín SpA | H102: 77316204 | I102: CGE COMERCIALIZADORA SPA | J102: Pago | K102: 7463 | L102: 6272 | M102: DISC_62246 | N102: 45111 | O102: Acreedor | P102: Pago | Q102: No | R102: =+MONTH(C102) | S102: 45141 | T102: 1025979 | W102: Pagado 21/7 | AB102: Cerrada | AC102: =+VLOOKUP(T102,'BBDD ACREEDORES'!$B:$C,2,0) | AE102: =IF(AB102="Abierta",V102,"Cerrada")
A103: Espera - Seguimiento Deudor - Cierre Anticipado - Seguimiento Acreedor - En Plazo de Regulación - Espera Movimientos - CANCELAR | B103: Cerrado | C103: 45126.678 | D103: - Sin Asignar - Usuario Pivot | E103: [DISC_62319][P][SEN_[BP__][May23][L][V01]][5562557] | F103: 763643441 | G103: PARQUE SOLAR FOTOVOLTAICO SOL DEL DESIERTO SpA | H103: 77316204 | I103: CGE COMERCIALIZADORA SPA | J103: Pago | K103: 101626 | L103: 85400 | M103: DISC_62319 | N103: 45111 | O103: Acreedor | P103: Pago | Q103: No | R103: =+MONTH(C103) | S103: 45141 | T103: 1026853 | W103: Pagado 21/7 | AB103: Cerrada | AC103: =+VLOOKUP(T103,'BBDD ACREEDORES'!$B:$C,2,0) | AE103: =IF(AB103="Abierta",V103,"Cerrada")
A104: Espera - Seguimiento Deudor - Cierre Anticipado - Seguimiento Acreedor - En Plazo de Regulación - Espera Movimientos - CANCELAR | B104: Cerrado | C104: 45126.678 | D104: - Sin Asignar - Usuario Pivot | E104: [DISC_62320][P][SEN_[TEE_][May23][L][V01]][5665838] | F104: 763643441 | G104: PARQUE SOLAR FOTOVOLTAICO SOL DEL DESIERTO SpA | H104: 77316204 | I104: CGE COMERCIALIZADORA SPA | J104: Pago | K104: 1582291 | L104: 1329657 | M104: DISC_62320 | N104: 45111 | O104: Acreedor | P104: Pago | Q104: No | R104: =+MONTH(C104) | S104: 45141 | T104: 1026853 | W104: Pagado 21/7 | AB104: Cerrada | AC104: =+VLOOKUP(T104,'BBDD ACREEDORES'!$B:$C,2,0) | AE104: =IF(AB104="Abierta",V104,"Cerrada")
A105: Espera - Seguimiento Deudor - Cierre Anticipado - Seguimiento Acreedor - En Plazo de Regulación - Espera Movimientos - CANCELAR | B105: Cerrado | C105: 45126.687 | D105: - Sin Asignar - Sebastián Parra - Usuario Pivot | E105: [DISC_62377][P][SEN_[BP__][May23][L][V01]][5562287] | F105: 769258000 | G105: ESPINOS S.A. | H105: 77316204 | I105: CGE COMERCIALIZADORA SPA | J105: Pago | K105: 330795 | L105: 277979 | M105: DISC_62377 | N105: 45111 | O105: Acreedor | P105: Pago | Q105: No | R105: =+MONTH(C105) | S105: 45141 | T105: 1007707 | W105: Pagado 21/7 | AB105: Cerrada | AC105: =+VLOOKUP(T105,'BBDD ACREEDORES'!$B:$C,2,0) | AE105: =IF(AB105="Abierta",V105,"Cerrada")
A106: Espera - Seguimiento Deudor - Cierre Anticipado - Seguimiento Acreedor - En Plazo de Regulación - Espera Movimientos - CANCELAR | B106: Cerrado | C106: 45126.688 | D106: - Sin Asignar - Sebastián Parra - Usuario Pivot | E106: [DISC_62387][P][SEN_[TEE_][May23][L][V01]][5665570] | F106: 769258000 | G106: ESPINOS S.A. | H106: 77316204 | I106: CGE COMERCIALIZADORA SPA | J106: Pago | K106: 332762 | L106: 279632 | M106: DISC_62387 | N106: 45111 | O106: Acreedor | P106: Pago | Q106: No | R106: =+MONTH(C106) | S106: 45141 | T106: 1007707 | W106: Pagado 21/7 | AB106: Cerrada | AC106: =+VLOOKUP(T106,'BBDD ACREEDORES'!$B:$C,2,0) | AE106: =IF(AB106="Abierta",V106,"Cerrada")
A107: Espera - Seguimiento Deudor - Cierre Anticipado - Seguimiento Acreedor - En Plazo de Regulación - Espera Movimientos - CANCELAR | B107: Cerrado | C107: 45126.744 | D107: - Sin Asignar - Usuario Pivot | E107: [DISC_62460][P][SEN_[CUN_][Dic22][L][V01]][5004504] | F107: 765197473 | G107: Sociedad Austral de Transmisión Troncal | H107: 77316204 | I107: CGE COMERCIALIZADORA SPA | J107: Pago | K107: 223825 | L107: 188089 | M107: DISC_62460 | N107: 44966 | O107: Acreedor | P107: Pago | Q107: No | R107: =+MONTH(C107) | S107: 45141 | T107: 1025213 | U107: 14404 | AB107: Cerrada | AC107: =+VLOOKUP(T107,'BBDD ACREEDORES'!$B:$C,2,0) | AE107: =IF(AB107="Abierta",V107,"Cerrada")
A108: Espera - Cierre Anticipado - Seguimiento Acreedor - En Plazo de Regulación - Seguimiento Deudor - Espera Movimientos - CANCELAR | B108: Cerrado | C108: 45126.954 | D108: - Sin Asignar - Javier Antonio Alemany Martínez - Usuario Pivot | E108: [DISC_62507][P][SEN_[BP__][May23][L][V01]][5562522] | F108: 764260295 | G108: Eléctrica Raso Power Ltda. | H108: 77316204 | I108: CGE COMERCIALIZADORA SPA | J108: Pago | K108: 11370 | L108: 9555 | M108: DISC_62507 | N108: 45111 | O108: Acreedor | P108: Pago | Q108: No | R108: =+MONTH(C108) | S108: 45141 | T108: 1025027 | W108: Pagado 21/7 | AB108: Cerrada | AC108: =+VLOOKUP(T108,'BBDD ACREEDORES'!$B:$C,2,0) | AE108: =IF(AB108="Abierta",V108,"Cerrada")
A109: Espera - Seguimiento Deudor - Cierre Anticipado - Seguimiento Acreedor - En Plazo de Regulación - Espera Movimientos - CANCELAR | B109: Cerrado | C109: 45131.579 | D109: - Sin Asignar - Usuario Pivot | E109: [DISC_63156][P][SEN_[BP__][May23][L][V01]][5562174] | F109: 762037882 | G109: Andes Generación SpA | H109: 77316204 | I109: CGE COMERCIALIZADORA SPA | J109: Pago | K109: 35647 | L109: 29956 | M109: DISC_63156 | N109: 45135.249 | O109: Acreedor | P109: Pago | Q109: No | R109: =+MONTH(C109) | S109: 45146 | T109: 1021658 | U109: 6884 | W109: Pagado 21/7 | AB109: Cerrada | AC109: =+VLOOKUP(T109,'BBDD ACREEDORES'!$B:$C,2,0) | AE109: =IF(AB109="Abierta",V109,"Cerrada")
A110: Espera - Seguimiento Deudor - Cierre Anticipado - Seguimiento Acreedor - En Plazo de Regulación - Espera Movimientos - CANCELAR | B110: Cerrado | C110: 45132.537 | D110: - Sin Asignar - Usuario Pivot | E110: [DISC_63437][P][SEN_[BP__][May23][L][V01]][5562223] | F110: 768663610 | G110: Chungungo Solar SpA | H110: 77316204 | I110: CGE COMERCIALIZADORA SPA | J110: Pago | K110: 3825 | L110: 3215 | M110: DISC_63437 | N110: 45138.207 | O110: Acreedor | P110: Pago | Q110: No | R110: =+MONTH(C110) | S110: 45141 | T110: 1026222 | U110: 4491 | W110: Pagado 21/7 | AB110: Cerrada | AC110: =+VLOOKUP(T110,'BBDD ACREEDORES'!$B:$C,2,0) | AE110: =IF(AB110="Abierta",V110,"Cerrada")
A111: Espera - Seguimiento Deudor - Cierre Anticipado - Seguimiento Acreedor - En Plazo de Regulación - Espera Movimientos - CANCELAR | B111: Cerrado | C111: 45132.538 | D111: - Sin Asignar - Usuario Pivot | E111: [DISC_63438][P][SEN_[TEE_][May23][L][V01]][5665511] | F111: 768663610 | G111: Chungungo Solar SpA | H111: 77316204 | I111: CGE COMERCIALIZADORA SPA | J111: Pago | K111: 141477 | L111: 118889 | M111: DISC_63438 | N111: 45138.207 | O111: Acreedor | P111: Pago | Q111: No | R111: =+MONTH(C111) | S111: 45146 | T111: 1026222 | U111: 4401 | W111: Pagado 21/7 | AB111: Cerrada | AC111: =+VLOOKUP(T111,'BBDD ACREEDORES'!$B:$C,2,0) | AE111: =IF(AB111="Abierta",V111,"Cerrada")
A112: Espera - Seguimiento Deudor - Cierre Anticipado - Seguimiento Acreedor - En Plazo de Regulación - Espera Movimientos - CANCELAR | B112: Cerrado | C112: 45132.572 | D112: - Sin Asignar - Usuario Pivot | E112: [DISC_63477][P][SEN_[BP__][May23][L][V01]][5562270] | F112: 760043370 | G112: Empresa Eléctrica Diego de Almagro SpA | H112: 77316204 | I112: CGE COMERCIALIZADORA SPA | J112: Pago | K112: 110536 | L112: 92888 | M112: DISC_63477 | N112: 45138.242 | O112: Acreedor | P112: Pago | Q112: No | R112: =+MONTH(C112) | S112: 45146 | T112: 1008987 | U112: 16912 | W112: Pagado 21/7 | AB112: Cerrada | AC112: =+VLOOKUP(T112,'BBDD ACREEDORES'!$B:$C,2,0) | AE112: =IF(AB112="Abierta",V112,"Cerrada")
A113: Espera - Seguimiento Deudor - Cierre Anticipado - Seguimiento Acreedor - En Plazo de Regulación - Espera Movimientos - CANCELAR | B113: Cerrado | C113: 45132.745 | D113: - Sin Asignar - Usuario Pivot | E113: [DISC_63609][P][SEN_[TEE_][May23][L][V01]][5665647] | F113: 760370363 | G113: Empresa Eléctrica La Arena SpA | H113: 77316204 | I113: CGE COMERCIALIZADORA SPA | J113: Pago | K113: 149778 | L113: 125864 | M113: DISC_63609 | N113: 45138.414 | O113: Acreedor | P113: Pago | Q113: No | S113: 45146 | T113: 1014070 | U113: 10589 | W113: Pagado 21/7 | AB113: Cerrada | AC113: =+VLOOKUP(T113,'BBDD ACREEDORES'!$B:$C,2,0) | AE113: =IF(AB113="Abierta",V113,"Cerrada")
...

Sheet BBDD ACREEDORES
A1: Razón Social Acreedor | B1: num acreedor | C1: RUT | D1: rut sin - | F1: 77.316.204-2 | G1: 77316204
A2: Innovación Energía S.A. | B2: 1025977 | C2: 76616538-9 | D2: =IFERROR(LEFT(C2,FIND("-",C2)-1),"")
A3: Andes Generación SpA | B3: 1021658 | C3: 76203788-2 | D3: =IFERROR(LEFT(C3,FIND("-",C3)-1),"")
A4: Transmisora Eléctrica del Norte S.A. | B4: 1024418 | C4: 76787690-4 | D4: =IFERROR(LEFT(C4,FIND("-",C4)-1),"")
A5: PFV Las Cachañas SpA | B5: 1027702 | D5: =IFERROR(LEFT(C5,FIND("-",C5)-1),"")
A6: Hidroelectrica Allipén S.A. | B6: 1015404 | C6: 76071891-2 | D6: =IFERROR(LEFT(C6,FIND("-",C6)-1),"")
A7: Hidroelectrica Trueno S.A. | B7: 1026449 | D7: =IFERROR(LEFT(C7,FIND("-",C7)-1),"")
A8: Hidroelectrica Puclaro S.A. | B8: 1014010 | D8: =IFERROR(LEFT(C8,FIND("-",C8)-1),"")
A9: Hidroeléctrica Mallarauco S.A. | B9: 1021439 | C9: 76055136-8 | D9: =IFERROR(LEFT(C9,FIND("-",C9)-1),"")
A10: Hidroeléctrica Río Huasco S.A. | B10: 1016827 | C10: 76071113-6 | D10: =IFERROR(LEFT(C10,FIND("-",C10)-1),"")
A11: Hidroeléctrica Embalse Ancoa SpA | B11: 1023872 | D11: =IFERROR(LEFT(C11,FIND("-",C11)-1),"")
A12: Hidroeléctrica Río Colorado S.A. | B12: 1023458 | D12: =IFERROR(LEFT(C12,FIND("-",C12)-1),"")
A13: Energía Pacífico S.A. | B13: 1013736 | C13: 76004531-4 | D13: =IFERROR(LEFT(C13,FIND("-",C13)-1),"")
A14: Colbún S.A. | B14: 1006828 | D14: =IFERROR(LEFT(C14,FIND("-",C14)-1),"")
A15: Central Yungay S.A. | B15: 1015580 | C15: 76060441-0 | D15: =IFERROR(LEFT(C15,FIND("-",C15)-1),"")
A16: Central Colmito S.A. | B16: 1020453 | C16: 76326949-3 | D16: =IFERROR(LEFT(C16,FIND("-",C16)-1),"")
A17: Enlasa Generación Chile S.A. | B17: 1007718 | C17: 76009328-9 | D17: =IFERROR(LEFT(C17,FIND("-",C17)-1),"")
A18: Chungungo Solar SpA | B18: 1026222 | C18: 76866361-0 | D18: =IFERROR(LEFT(C18,FIND("-",C18)-1),"")
A19: Empresa Eléctrica Diego de Almagro SpA | B19: 1008987 | C19: 76004337-0 | D19: =IFERROR(LEFT(C19,FIND("-",C19)-1),"")
A20: Empresa Eléctrica La Arena SpA | B20: 1014070 | C20: 76037036-3 | D20: =IFERROR(LEFT(C20,FIND("-",C20)-1),"")
A21: Empresa Eléctrica Tranquil S.P.A | B21: 1023007 | D21: =IFERROR(LEFT(C21,FIND("-",C21)-1),"")
A22: Generación de Energía Nueva Degan SpA | B22: 1016242 | C22: 76265287-0 | D22: =IFERROR(LEFT(C22,FIND("-",C22)-1),"")
A23: Generadora Antilhue Spa | B23: 1025760 | C23: 76009904-K | D23: =IFERROR(LEFT(C23,FIND("-",C23)-1),"")
A24: Inversiones Chacabuco SpA | B24: 1026424 | C24: 77252945-7 | D24: =IFERROR(LEFT(C24,FIND("-",C24)-1),"")
A25: Solar la Blanquina SpA | B25: 1026425 | C25: 77261956-1 | D25: =IFERROR(LEFT(C25,FIND("-",C25)-1),"")
A26: Fontus Prime Solar SpA | B26: 1027439 | C26: 77042032-6 | D26: =IFERROR(LEFT(C26,FIND("-",C26)-1),"")
A27: Generadora del Pacifico SpA | B27: 1008148 | C27: 76010367-5 | D27: =IFERROR(LEFT(C27,FIND("-",C27)-1),"")
A28: Prime Energía Quickstart SpA | B28: 1026410 | C28: 76452055-6 | D28: =IFERROR(LEFT(C28,FIND("-",C28)-1),"")
A29: Alto Cautín SpA | B29: 1025979 | D29: =IFERROR(LEFT(C29,FIND("-",C29)-1),"")
A30: ESPINOS S.A. | B30: 1007707 | D30: =IFERROR(LEFT(C30,FIND("-",C30)-1),"")
A31: SOCIEDAD GENERADORA AUSTRAL S.A. | B31: 1007708 | D31: =IFERROR(LEFT(C31,FIND("-",C31)-1),"")
A32: Enap Refinerias S.A. | B32: 1008529 | D32: =IFERROR(LEFT(C32,FIND("-",C32)-1),"")
A33: Sonnedix Parque Eólico El Arrayán SpA | B33: 1017381 | D33: =IFERROR(LEFT(C33,FIND("-",C33)-1),"")
A34: Electrica Nueva Energía S.A. | B34: 1007717 | C34: 76045612-8 | D34: =IFERROR(LEFT(C34,FIND("-",C34)-1),"")
A35: Central Cardones S.A. | B35: 1010018 | C35: 76550580-1 | D35: =IFERROR(LEFT(C35,FIND("-",C35)-1),"")
A36: SISTEMA DE TRANSMISIÓN DEL NORTE S.A. | B36: 1025221 | C36: 76410374-2 | D36: =IFERROR(LEFT(C36,FIND("-",C36)-1),"")
A37: Energía Atacama S.A. | B37: 1018350 | D37: =IFERROR(LEFT(C37,FIND("-",C37)-1),"")
A38: Sonnedix Energy Trading Chile SpA | B38: 1026655 | C38: 77257713-3 | D38: =IFERROR(LEFT(C38,FIND("-",C38)-1),"")
A39: Ibereólica Cabo Leones II S.A. | B39: 1025180 | C39: 76202178-1 | D39: =IFERROR(LEFT(C39,FIND("-",C39)-1),"")
A40: PARQUE SOLAR H6 | B40: 1025825 | D40: =IFERROR(LEFT(C40,FIND("-",C40)-1),"")
A41: Hidroeléctrica Río Lircay S.A. | B41: 1013571 | D41: =IFERROR(LEFT(C41,FIND("-",C41)-1),"")
A42: Elektra Generación S.A. | B42: 1007706 | C42: 76594660-3 | D42: =IFERROR(LEFT(C42,FIND("-",C42)-1),"")
A43: Fotovoltaica Norte Grande 5 SpA | B43: 1023433 | D43: =IFERROR(LEFT(C43,FIND("-",C43)-1),"")
A44: ELECTRICA PINARES LTDA | B44: 1026485 | C44: 77053312-0 | D44: =IFERROR(LEFT(C44,FIND("-",C44)-1),"")
A45: Sistema de Transmisión del Sur S.A. | B45: 1006425 | C45: 77312201-6 | D45: =IFERROR(LEFT(C45,FIND("-",C45)-1),"")
A46: PARQUE SOLAR FOTOVOLTAICO SOL DEL DESIERTO SpA | B46: 1026853 | C46: 76364344-1 | D46: =IFERROR(LEFT(C46,FIND("-",C46)-1),"")
A47: Sociedad Austral de Transmisión Troncal | B47: 1025213 | C47: 76519747-3 | D47: =IFERROR(LEFT(C47,FIND("-",C47)-1),"")
A48: Eléctrica Raso Power Ltda. | B48: 1025027 | C48: 76426029-5 | D48: =IFERROR(LEFT(C48,FIND("-",C48)-1),"")
A49: Cooperativa de Abastecimiento de Energía Eléctrica Curico LTDA. | B49: 1007022 | D49: =IFERROR(LEFT(C49,FIND("-",C49)-1),"")
A50: Eléctrica Cipresillos SpA | B50: 1026371 | C50: 76282509-0 | D50: =IFERROR(LEFT(C50,FIND("-",C50)-1),"")
A51: Enel Generación Chile S.A. | B51: 1007720 | C51: 91081000-6 | D51: =IFERROR(LEFT(C51,FIND("-",C51)-1),"")
A52: Parque Eólico Atacama SpA | B52: 1028027 | C52: 76852769-5 | D52: =IFERROR(LEFT(C52,FIND("-",C52)-1),"")
A53: Empresa Eléctrica Pehuenche S.A. | B53: 1007723 | C53: 96504980-0 | D53: =IFERROR(LEFT(C53,FIND("-",C53)-1),"")
A54: CE CENTINELA SOLAR SPA | B54: 1028015 | C54: 77070574-6 | D54: =IFERROR(LEFT(C54,FIND("-",C54)-1),"")
A55: Hidroangol S.A. | B55: 1019755 | D55: =IFERROR(LEFT(C55,FIND("-",C55)-1),"")
A56: Hidroenersur S.A. | B56: 1025975 | D56: =IFERROR(LEFT(C56,FIND("-",C56)-1),"")
A57: Hidromocho S.A. | B57: 1026450 | D57: =IFERROR(LEFT(C57,FIND("-",C57)-1),"")
A58: CE Uribe de Antofagasta Solar SpA | B58: 1028016 | C58: 77266042-1 | D58: =IFERROR(LEFT(C58,FIND("-",C58)-1),"")
A59: GR ALERCE ANDINO SPA | B59: 1027735 | D59: =IFERROR(LEFT(C59,FIND("-",C59)-1),"")
A60: GR Ruil SpA | B60: 1027431 | C60: 76885337-1 | D60: =IFERROR(LEFT(C60,FIND("-",C60)-1),"")
A61: Chungungo S.A. | B61: 1020914 | C61: 76392147-6 | D61: =IFERROR(LEFT(C61,FIND("-",C61)-1),"")
A62: Mytilineos Energy Trading Chile SpA | B62: 1028047 | D62: =IFERROR(LEFT(C62,FIND("-",C62)-1),"")
A63: ENEL GREEN POWER CHILE S.A. | B63: 1021550 | C63: 76412562-2 | D63: =IFERROR(LEFT(C63,FIND("-",C63)-1),"")
A64: Geotérmica del Norte S.A. | B64: 1024224 | D64: =IFERROR(LEFT(C64,FIND("-",C64)-1),"")
A65: Parque Talinay Oriente S.A. | B65: 1016158 | D65: =IFERROR(LEFT(C65,FIND("-",C65)-1),"")
A66: Hidroeléctrica El Paso SpA | B66: 1026061 | D66: =IFERROR(LEFT(C66,FIND("-",C66)-1),"")
A67: FV SANTA LAURA SPA | B67: 1026013 | C67: 76954708-8 | D67: =IFERROR(LEFT(C67,FIND("-",C67)-1),"")
A68: EOLICO LAS PEÑAS SPA | B68: 1026448 | C68: 76389157-7 | D68: =IFERROR(LEFT(C68,FIND("-",C68)-1),"")
A69: PFV EL CÓNDOR SPA | B69: 1026071 | D69: =IFERROR(LEFT(C69,FIND("-",C69)-1),"")
A70: Red Eléctrica del Norte 2 S.A. | B70: 1025220 | D70: =IFERROR(LEFT(C70,FIND("-",C70)-1),"")
A71: Red Eléctrica del Norte S.A. | B71: 1026214 | C71: 76766227-0 | D71: =IFERROR(LEFT(C71,FIND("-",C71)-1),"")
A72: Energia Siete SpA | B72: 1025992 | C72: 76335523-3 | D72: =IFERROR(LEFT(C72,FIND("-",C72)-1),"")
A73: Interchile S.A. | B73: 1024580 | D73: =IFERROR(LEFT(C73,FIND("-",C73)-1),"")
A74: Agrícola Ancalí Ltda | B74: 1028034 | D74: =IFERROR(LEFT(C74,FIND("-",C74)-1),"")
A75: ENERGY PARTNERS SpA | B75: 1028301 | C75: 77410232-9 | D75: =IFERROR(LEFT(C75,FIND("-",C75)-1),"")
A76: Parque Solar Quetena S.A. | B76: 1027225 | D76: =IFERROR(LEFT(C76,FIND("-",C76)-1),"")
A77: Mataquito Transmisora de Energía S.A. | B77: 1027347 | C77: 76951331-0 | D77: =IFERROR(LEFT(C77,FIND("-",C77)-1),"")
A78: PFV Las Tencas SpA | B78: 1027227 | D78: =IFERROR(LEFT(C78,FIND("-",C78)-1),"")
A79: Sonnedix La Serena Spa | B79: 1026076 | C79: 77131323-K | D79: =IFERROR(LEFT(C79,FIND("-",C79)-1),"")
A80: MAGDALENA SOLAR SPA | B80: 1028018 | D80: =IFERROR(LEFT(C80,FIND("-",C80)-1),"")
A81: El Olivar Solar SpA | B81: 1028024 | D81: =IFERROR(LEFT(C81,FIND("-",C81)-1),"")
A82: Hidroeléctrica Maisán SpA | B82: 1017371 | D82: =IFERROR(LEFT(C82,FIND("-",C82)-1),"")
A83: Hidroeléctrica Trailelfu SpA | B83: 1022153 | D83: =IFERROR(LEFT(C83,FIND("-",C83)-1),"")
A84: Generadora Los Hibiscos SpA. | B84: 1028013 | D84: =IFERROR(LEFT(C84,FIND("-",C84)-1),"")
A85: Generadora Mimbre SpA. | B85: 1026415 | C85: 76.761.555-8 | D85: =IFERROR(LEFT(C85,FIND("-",C85)-1),"")
A86: Imelsa Energia SpA | B86: 1020945 | C86: 76472262-0 | D86: =IFERROR(LEFT(C86,FIND("-",C86)-1),"")
A87: Parque Solar Los Lirios II SpA | B87: 1027743 | D87: =IFERROR(LEFT(C87,FIND("-",C87)-1),"")
A88: CINERGIA Chile SpA | B88: 1026464 | D88: =IFERROR(LEFT(C88,FIND("-",C88)-1),"")
A89: INVERSIONES FOTOVOLTAICAS SPA | B89: 1028361 | C89: 76319461-2 | D89: =IFERROR(LEFT(C89,FIND("-",C89)-1),"")
A90: GR CHAQUIHUE SpA | B90: 1025994 | C90: 76.461.944-7 | D90: =IFERROR(LEFT(C90,FIND("-",C90)-1),"")
A91: BTG PACTUAL CHILE SPA | B91: 1028433 | D91: =IFERROR(LEFT(C91,FIND("-",C91)-1),"")
A92: SOLAR TI DIECISIETE SPA | B92: 1028014 | C92: 77011882-4 | D92: =IFERROR(LEFT(C92,FIND("-",C92)-1),"")
A93: Solar Ti Quince SpA | B93: 1028250 | D93: =IFERROR(LEFT(C93,FIND("-",C93)-1),"")
A94: Punta Palmeras S.A. | B94: 1017942 | D94: =IFERROR(LEFT(C94,FIND("-",C94)-1),"")
A95: Guacolda Energía SpA. | B95: 1019751 | C95: 76418918-3 | D95: =IFERROR(LEFT(C95,FIND("-",C95)-1),"")
A96: PSF Quemados SpA | B96: 1028075 | D96: =IFERROR(LEFT(C96,FIND("-",C96)-1),"")
A97: MGM Innova Capital Chile SpA | B97: 1026068 | D97: =IFERROR(LEFT(C97,FIND("-",C97)-1),"")
A98: Chilener II SpA | B98: 1028413 | D98: =IFERROR(LEFT(C98,FIND("-",C98)-1),"")
A99: Teno III SpA | B99: 1028414 | D99: =IFERROR(LEFT(C99,FIND("-",C99)-1),"")
A100: MARIA ELENA SOLAR EN LIQUIDACION CONCURSAL S.A. | B100: 1026067 | D100: =IFERROR(LEFT(C100,FIND("-",C100)-1),"")
...

Sheet Consultas ALE
A1: Activity | B1: Estado de la tarea | C1: Fecha Creación del caso hasta | D1: Current User - Full Name | E1: Nemotécnico | F1: Rut Acreedor | G1: Razón Social Acreedor | H1: Rut Deudor | I1: Razón Social Deudor | J1: Tipo de Disconformidad | K1: Monto bruto instrucción de pago | L1: Saldo Pendiente (Neto) | M1: Número de Disconformidad | N1: Fecha de Vencimiento Desde | O1: ¿Disconformidad Abierta por? | P1: Tipo de Disconformidad | Q1: En Espera de Ejecución | R1: Mes | S1: Plazo (10 Dias hab) | T1: N° Acreedor | U1: N° factura | V1: Emisión | W1: OC | X1: HES
A2: Esperar Para Avanzar - Realizar Seguimiento Deudor - Realizar Seguimiento Acreedor - Cerrar Anticipado - Gestionar en Plazo de Regulación - Cancelar - Esperar Movimientos | B2: A tiempo - A tiempo - A tiempo - A tiempo - En riesgo - A tiempo - A tiempo | C2: 45970.098 | D2: - Sin Asignar | E2: [DISC_349677][P][SEN_[TEE_][May24][L][V01]][7626493] | F2: 77271459 | G2: ALTO BELLAVISTA SPA | H2: 77316204 | I2: CGE COMERCIALIZADORA SPA | J2: Pago | K2: 12171 | L2: 10228 | M2: DISC_349677 | N2: 45980.458 | O2: 45785 | P2: Acreedor | Q2: TEE_ | R2: =+MONTH(C2) | S2: =WORKDAY(C2,10) | T2: =+_xlfn.XLOOKUP(G2,'BBDD ACREEDORES'!$A:$A,'BBDD ACREEDORES'!$B:$B,"",0,1) | U2: 3395 | V2: En Gestion | W2: 41987220 | X2: 1003161596 | Z2: Enviadas a ingreso a pago | AA2: Ale | AB2: Abierta | AC2: =+VLOOKUP(T2,'BBDD ACREEDORES'!$B:$C,2,0)
A24: Razón Social Acreedor | B24: Monto bruto instrucción de pago | C24: Saldo Pendiente (Neto) | D24: Número de Disconformidad | E24: N° Acreedor | F24: N° factura | G24: Rut | H24: OC/HES | I24: OC | J24: HES
A25: =+G2 | B25: =K2 | C25: =+L2 | D25: =+M2 | E25: =+T2 | F25: =+U2 | G25: =+VLOOKUP(T2,'BBDD ACREEDORES'!$B:$C,2,0) | H25: =+N2 | I25: =+W2 | J25: =+X2
A26: =+G3 | B26: =K3 | C26: =+L3 | D26: =+M3 | E26: =+T3 | F26: =+U3 | G26: =+VLOOKUP(T3,'BBDD ACREEDORES'!$B:$C,2,0) | H26: =+N3 | I26: =+W3 | J26: =+X3 | K26: =+_xlfn.XLOOKUP(I26,'BBDD ACREEDORES'!$D:$D,'BBDD ACREEDORES'!C:C,"",0,1)
A27: =+G4 | B27: =K4 | C27: =+L4 | D27: =+M4 | E27: =+T4 | F27: =+U4 | G27: =+VLOOKUP(T4,'BBDD ACREEDORES'!$B:$C,2,0) | H27: =+N4 | I27: =+W4 | J27: =+X4 | K27: =+_xlfn.XLOOKUP(I27,'BBDD ACREEDORES'!$D:$D,'BBDD ACREEDORES'!C:C,"",0,1)
A28: =+G5 | B28: =K5 | C28: =+L5 | D28: =+M5 | E28: =+T5 | F28: =+U5 | G28: =+VLOOKUP(T5,'BBDD ACREEDORES'!$B:$C,2,0) | H28: =+N5 | I28: =+W5 | J28: =+X5 | K28: =+_xlfn.XLOOKUP(I28,'BBDD ACREEDORES'!$D:$D,'BBDD ACREEDORES'!C:C,"",0,1)
A29: =+G6 | B29: =K6 | C29: =+L6 | D29: =+M6 | E29: =+T6 | F29: =+U6 | G29: =+VLOOKUP(T6,'BBDD ACREEDORES'!$B:$C,2,0) | H29: =+N6 | I29: =+W6 | J29: =+X6
A30: =+G7 | B30: =K7 | C30: =+L7 | D30: =+M7 | E30: =+T7 | F30: =+U7 | G30: =+VLOOKUP(T7,'BBDD ACREEDORES'!$B:$C,2,0) | H30: =+N7 | I30: =+W7 | J30: =+X7
A31: =+G8 | B31: =K8 | C31: =+L8 | D31: =+M8 | E31: =+T8 | F31: =+U8 | G31: =+VLOOKUP(T8,'BBDD ACREEDORES'!$B:$C,2,0) | H31: =+N8 | I31: =+W8 | J31: =+X8
A32: =+G9 | B32: =K9 | C32: =+L9 | D32: =+M9 | E32: =+T9 | F32: =+U9 | G32: =+VLOOKUP(T9,'BBDD ACREEDORES'!$B:$C,2,0) | H32: =+N9 | I32: =+W9 | J32: =+X9
A33: =+G10 | B33: =K10 | C33: =+L10 | D33: =+M10 | E33: =+T10 | F33: =+U10 | G33: =+VLOOKUP(T10,'BBDD ACREEDORES'!$B:$C,2,0) | H33: =+N10 | I33: =+W10 | J33: =+X10
A34: =+G11 | B34: =K11 | C34: =+L11 | D34: =+M11 | E34: =+T11 | F34: =+U11 | G34: =+VLOOKUP(T11,'BBDD ACREEDORES'!$B:$C,2,0) | H34: =+N11 | I34: =+W11 | J34: =+X11
A35: =+G12 | B35: =K12 | C35: =+L12 | D35: =+M12 | E35: =+T12 | F35: =+U12 | G35: =+VLOOKUP(T12,'BBDD ACREEDORES'!$B:$C,2,0) | H35: =+N12 | I35: =+W12 | J35: =+X12
A36: =+G13 | B36: =K13 | C36: =+L13 | D36: =+M13 | E36: =+T13 | F36: =+U13 | G36: =+VLOOKUP(T13,'BBDD ACREEDORES'!$B:$C,2,0) | H36: =+N13 | I36: =+W13 | J36: =+X13
A37: =+G14 | B37: =K14 | C37: =+L14 | D37: =+M14 | E37: =+T14 | F37: =+U14 | G37: =+VLOOKUP(T14,'BBDD ACREEDORES'!$B:$C,2,0) | H37: =+N14 | I37: =+W14 | J37: =+X14
A38: =+G15 | B38: =K15 | C38: =+L15 | D38: =+M15 | E38: =+T15 | F38: =+U15 | G38: =+VLOOKUP(T15,'BBDD ACREEDORES'!$B:$C,2,0) | H38: =+N15 | I38: =+W15 | J38: =+X15
A39: =+G16 | B39: =K16 | C39: =+L16 | D39: =+M16 | E39: =+T16 | F39: =+U16 | G39: =+VLOOKUP(T16,'BBDD ACREEDORES'!$B:$C,2,0) | H39: =+N16 | I39: =+W16 | J39: =+X16
A40: =+G17 | B40: =K17 | C40: =+L17 | D40: =+M17 | E40: =+T17 | F40: =+U17 | G40: =+VLOOKUP(T17,'BBDD ACREEDORES'!$B:$C,2,0) | H40: =+N17 | I40: =+W17 | J40: =+X17
A41: =+G18 | B41: =K18 | C41: =+L18 | D41: =+M18 | E41: =+T18 | F41: =+U18 | G41: =+VLOOKUP(T18,'BBDD ACREEDORES'!$B:$C,2,0) | H41: =+N18 | I41: =+W18 | J41: =+X18

Sheet Consultas  Victoria
A1: Activity | B1: Estado de la tarea | C1: Fecha Creación del caso hasta | D1: Current User - Full Name | E1: Nemotécnico | F1: Rut Acreedor | G1: Razón Social Acreedor | H1: Rut Deudor | I1: Razón Social Deudor | J1: Tipo de Disconformidad | K1: Monto bruto instrucción de pago | L1: Saldo Pendiente (Neto) | M1: Número de Disconformidad | N1: Fecha de Vencimiento Desde | O1: ¿Disconformidad Abierta por? | P1: Tipo de Disconformidad | Q1: En Espera de Ejecución | R1: Mes | S1: Plazo (10 Dias hab) | T1: N° Acreedor | U1: N° factura | V1: Emisión | W1: Emisión
A2: Esperar Para Avanzar - Realizar Seguimiento Deudor - Realizar Seguimiento Acreedor - Cerrar Anticipado - Gestionar en Plazo de Regulación - Cancelar - Esperar Movimientos | B2: A tiempo - A tiempo - A tiempo - A tiempo - En riesgo - A tiempo - A tiempo | C2: 45970.098 | D2: - Sin Asignar | E2: [DISC_349677][P][SEN_[TEE_][May24][L][V01]][7626493] | F2: 77271459 | G2: ALTO BELLAVISTA SPA | H2: 77316204 | I2: CGE COMERCIALIZADORA SPA | J2: Pago | K2: 12171 | L2: 10228 | M2: DISC_349677 | N2: 45980.458 | O2: 45785 | P2: Acreedor | Q2: TEE_ | R2: =+MONTH(C2) | S2: =WORKDAY(C2,10) | T2: =+_xlfn.XLOOKUP(G2,'BBDD ACREEDORES'!$A:$A,'BBDD ACREEDORES'!$B:$B,"",0,1) | U2: 3395
D20: Rut | E20: Nemotécnico | F20: Razón Social Acreedor | G20: Monto bruto instrucción de pago | H20: Saldo Pendiente (Neto) | I20: Número de Disconformidad | J20: N° Acreedor | K20: N° factura
D21: =+_xlfn.XLOOKUP(J21,'BBDD ACREEDORES'!$B:$B,'BBDD ACREEDORES'!$C:$C,"",0,1) | E21: =+E2 | F21: =+G2 | G21: =+K2 | H21: =+L2 | I21: =+M2 | J21: =+T2 | K21: =+U2
D22: =+_xlfn.XLOOKUP(J22,'BBDD ACREEDORES'!$B:$B,'BBDD ACREEDORES'!$C:$C,"",0,1) | E22: =+E3 | F22: =+G3 | G22: =+K3 | H22: =+L3 | I22: =+M3 | J22: =+T3 | K22: =+U3
D23: =+_xlfn.XLOOKUP(J23,'BBDD ACREEDORES'!$B:$B,'BBDD ACREEDORES'!$C:$C,"",0,1) | E23: =+E4 | F23: =+G4 | G23: =+K4 | H23: =+L4 | I23: =+M4 | J23: =+T4 | K23: =+U4
D24: =+_xlfn.XLOOKUP(J24,'BBDD ACREEDORES'!$B:$B,'BBDD ACREEDORES'!$C:$C,"",0,1) | E24: =+E5 | F24: =+G5 | G24: =+K5 | H24: =+L5 | I24: =+M5 | J24: =+T5 | K24: =+U5
D25: =+_xlfn.XLOOKUP(J25,'BBDD ACREEDORES'!$B:$B,'BBDD ACREEDORES'!$C:$C,"",0,1) | E25: =+E6 | F25: =+G6 | G25: =+K6 | H25: =+L6 | I25: =+M6 | J25: =+T6 | K25: =+U6
D26: =+_xlfn.XLOOKUP(J26,'BBDD ACREEDORES'!$B:$B,'BBDD ACREEDORES'!$C:$C,"",0,1) | E26: =+E7 | F26: =+G7 | G26: =+K7 | H26: =+L7 | I26: =+M7 | J26: =+T7 | K26: =+U7
D27: =+_xlfn.XLOOKUP(J27,'BBDD ACREEDORES'!$B:$B,'BBDD ACREEDORES'!$C:$C,"",0,1) | E27: =+E8 | F27: =+G8 | G27: =+K8 | H27: =+L8 | I27: =+M8 | J27: =+T8 | K27: =+U8
D28: =+_xlfn.XLOOKUP(J28,'BBDD ACREEDORES'!$B:$B,'BBDD ACREEDORES'!$C:$C,"",0,1) | E28: =+E9 | F28: =+G9 | G28: =+K9 | H28: =+L9 | I28: =+M9 | J28: =+T9 | K28: =+U9
D29: =+_xlfn.XLOOKUP(J29,'BBDD ACREEDORES'!$B:$B,'BBDD ACREEDORES'!$C:$C,"",0,1) | E29: =+E10 | F29: =+G10 | G29: =+K10 | H29: =+L10 | I29: =+M10 | J29: =+T10 | K29: =+U10
D30: =+_xlfn.XLOOKUP(J30,'BBDD ACREEDORES'!$B:$B,'BBDD ACREEDORES'!$C:$C,"",0,1) | E30: =+E11 | F30: =+G11 | G30: =+K11 | H30: =+L11 | I30: =+M11 | J30: =+T11 | K30: =+U11
D31: =+_xlfn.XLOOKUP(J31,'BBDD ACREEDORES'!$B:$B,'BBDD ACREEDORES'!$C:$C,"",0,1) | E31: =+E12 | F31: =+G12 | G31: =+K12 | H31: =+L12 | I31: =+M12 | J31: =+T12 | K31: =+U12
D32: =+_xlfn.XLOOKUP(J32,'BBDD ACREEDORES'!$B:$B,'BBDD ACREEDORES'!$C:$C,"",0,1) | E32: =+E13 | F32: =+G13 | G32: =+K13 | H32: =+L13 | I32: =+M13 | J32: =+T13 | K32: =+U13
D33: =+_xlfn.XLOOKUP(J33,'BBDD ACREEDORES'!$B:$B,'BBDD ACREEDORES'!$C:$C,"",0,1) | E33: =+E14 | F33: =+G14 | G33: =+K14 | H33: =+L14 | I33: =+M14 | J33: =+T14 | K33: =+U14

Sheet Hoja2
M4: Número de Disconformidad | N4: Fecha de Vencimiento Desde | O4: ¿Disconformidad Abierta por? | P4: Tipo de Disconformidad | Q4: En Espera de Ejecución | R4: Mes | S4: Plazo | T4: N° Acreedor | U4: N° factura
M5: DISC_114242 | N5: 45159 | O5: Acreedor | P5: Pago | Q5: No | R5: 3 | S5: 45372 | T5: 1025974 | U5: 8938
B22: coordinador
B36: buscar si llego la factura
B37: Rut Acreedor | C37: Razón Social Acreedor | D37: N° Acreedor | E37: N° factura
B38: 768372721 | C38: Hidroconfianza SpA | D38: 1028470 | E38: 128 | F38: revisar si llego la factura
B39: 76985186 | C39: Blu Solar SpA | D39: 1028412 | E39: 729 | F39: comprobantes de pago | G39: se pagaron 2 facturas (1305+43727=45.032)
B40: 76985186 | C40: Blu Solar SpA | D40: 1028412 | E40: 787 | F40: comprobantes de pago | G40: se pagaron 2 facturas (1305+43727=45.032)
B41: 70287900 | C41: Cooperativa de Abastecimiento de Energía Eléctrica Curico LTDA. | D41: 1007022 | E41: 353409 | F41: comprobantes de pago | G41: se pagaron 2 facturas (19+3929=3.948)
